{
"meta":{"test_sets":[],"test_metrics":[],"learn_metrics":[{"best_value":"Min","name":"RMSE"}],"launch_mode":"Train","parameters":"","iteration_count":1000,"learn_sets":["learn"],"name":"experiment"},
"iterations":[
{"learn":[14.61268541],"iteration":0,"passed_time":0.1407429197,"remaining_time":140.6021768},
{"learn":[14.23196558],"iteration":1,"passed_time":0.1419469133,"remaining_time":70.83150975},
{"learn":[13.86674177],"iteration":2,"passed_time":0.1430631856,"remaining_time":47.54466533},
{"learn":[13.49946468],"iteration":3,"passed_time":0.1440015713,"remaining_time":35.85639125},
{"learn":[13.16661202],"iteration":4,"passed_time":0.1449162616,"remaining_time":28.83833605},
{"learn":[12.85632158],"iteration":5,"passed_time":0.1459472761,"remaining_time":24.17859873},
{"learn":[12.56784336],"iteration":6,"passed_time":0.1469399932,"remaining_time":20.84448761},
{"learn":[12.31617801],"iteration":7,"passed_time":0.147890437,"remaining_time":18.33841419},
{"learn":[12.01509946],"iteration":8,"passed_time":0.1488151122,"remaining_time":16.38619736},
{"learn":[11.71512571],"iteration":9,"passed_time":0.149732837,"remaining_time":14.82355086},
{"learn":[11.43264457],"iteration":10,"passed_time":0.1506704616,"remaining_time":13.54664423},
{"learn":[11.17973129],"iteration":11,"passed_time":0.1515684168,"remaining_time":12.47913298},
{"learn":[10.93746433],"iteration":12,"passed_time":0.1523920006,"remaining_time":11.57006958},
{"learn":[10.69387075],"iteration":13,"passed_time":0.1531433061,"remaining_time":10.78566427},
{"learn":[10.4615922],"iteration":14,"passed_time":0.1539178564,"remaining_time":10.10727257},
{"learn":[10.2299235],"iteration":15,"passed_time":0.1545594575,"remaining_time":9.505406638},
{"learn":[10.01419731],"iteration":16,"passed_time":0.1553097315,"remaining_time":8.980556826},
{"learn":[9.795856918],"iteration":17,"passed_time":0.156032995,"remaining_time":8.512466725},
{"learn":[9.60040151],"iteration":18,"passed_time":0.1567610056,"remaining_time":8.093818234},
{"learn":[9.418664989],"iteration":19,"passed_time":0.1574521609,"remaining_time":7.715155886},
{"learn":[9.249278645],"iteration":20,"passed_time":0.1581388797,"remaining_time":7.372283962},
{"learn":[9.090113396],"iteration":21,"passed_time":0.1588692638,"remaining_time":7.06246091},
{"learn":[8.909548708],"iteration":22,"passed_time":0.1595330582,"remaining_time":6.776686864},
{"learn":[8.740140208],"iteration":23,"passed_time":0.1602680292,"remaining_time":6.517566522},
{"learn":[8.59377682],"iteration":24,"passed_time":0.1609891395,"remaining_time":6.27857644},
{"learn":[8.453885414],"iteration":25,"passed_time":0.1616822678,"remaining_time":6.056866495},
{"learn":[8.317732234],"iteration":26,"passed_time":0.1624070937,"remaining_time":5.852670449},
{"learn":[8.180896085],"iteration":27,"passed_time":0.16309222,"remaining_time":5.661629923},
{"learn":[8.053220863],"iteration":28,"passed_time":0.1638056187,"remaining_time":5.484663992},
{"learn":[7.924234474],"iteration":29,"passed_time":0.1645137395,"remaining_time":5.319277578},
{"learn":[7.818879511],"iteration":30,"passed_time":0.165167569,"remaining_time":5.162818527},
{"learn":[7.719346395],"iteration":31,"passed_time":0.1658694304,"remaining_time":5.01755027},
{"learn":[7.624163594],"iteration":32,"passed_time":0.1665740059,"remaining_time":4.881123143},
{"learn":[7.524952543],"iteration":33,"passed_time":0.1673177901,"remaining_time":4.753793684},
{"learn":[7.424464745],"iteration":34,"passed_time":0.1680277337,"remaining_time":4.632764656},
{"learn":[7.327482321],"iteration":35,"passed_time":0.1687283132,"remaining_time":4.518169274},
{"learn":[7.238666841],"iteration":36,"passed_time":0.1694487624,"remaining_time":4.410247519},
{"learn":[7.158842395],"iteration":37,"passed_time":0.1701298327,"remaining_time":4.306971028},
{"learn":[7.074348246],"iteration":38,"passed_time":0.1708204072,"remaining_time":4.209190034},
{"learn":[6.992269093],"iteration":39,"passed_time":0.1715158991,"remaining_time":4.116381578},
{"learn":[6.925219745],"iteration":40,"passed_time":0.1722014861,"remaining_time":4.027834761},
{"learn":[6.86013671],"iteration":41,"passed_time":0.172902286,"remaining_time":3.943818808},
{"learn":[6.786739622],"iteration":42,"passed_time":0.1735724699,"remaining_time":3.862996598},
{"learn":[6.73057926],"iteration":43,"passed_time":0.1742704155,"remaining_time":3.786420846},
{"learn":[6.666356486],"iteration":44,"passed_time":0.1749625123,"remaining_time":3.713093316},
{"learn":[6.606182832],"iteration":45,"passed_time":0.1756574033,"remaining_time":3.642981798},
{"learn":[6.547854615],"iteration":46,"passed_time":0.1764737568,"remaining_time":3.578287025},
{"learn":[6.49240675],"iteration":47,"passed_time":0.1771657834,"remaining_time":3.513788038},
{"learn":[6.431317261],"iteration":48,"passed_time":0.1778654916,"remaining_time":3.452042501},
{"learn":[6.377586395],"iteration":49,"passed_time":0.1785648493,"remaining_time":3.392732137},
{"learn":[6.327558015],"iteration":50,"passed_time":0.1792751233,"remaining_time":3.335923374},
{"learn":[6.282040317],"iteration":51,"passed_time":0.1799954925,"remaining_time":3.281456286},
{"learn":[6.237655841],"iteration":52,"passed_time":0.180713418,"remaining_time":3.228973714},
{"learn":[6.192792003],"iteration":53,"passed_time":0.1814854746,"remaining_time":3.179356647},
{"learn":[6.150579347],"iteration":54,"passed_time":0.1821659239,"remaining_time":3.129941783},
{"learn":[6.115693845],"iteration":55,"passed_time":0.1828766486,"remaining_time":3.082777791},
{"learn":[6.078780782],"iteration":56,"passed_time":0.1835804529,"remaining_time":3.037129248},
{"learn":[6.045146957],"iteration":57,"passed_time":0.1842809423,"remaining_time":2.992976684},
{"learn":[6.008080327],"iteration":58,"passed_time":0.1849675509,"remaining_time":2.950075684},
{"learn":[5.977575734],"iteration":59,"passed_time":0.1856470788,"remaining_time":2.908470902},
{"learn":[5.948036502],"iteration":60,"passed_time":0.1863484395,"remaining_time":2.868544011},
{"learn":[5.914888282],"iteration":61,"passed_time":0.1870720535,"remaining_time":2.830219132},
{"learn":[5.884957796],"iteration":62,"passed_time":0.1877650316,"remaining_time":2.792632296},
{"learn":[5.849539885],"iteration":63,"passed_time":0.1884658515,"remaining_time":2.756313078},
{"learn":[5.821387627],"iteration":64,"passed_time":0.1891715887,"remaining_time":2.721160545},
{"learn":[5.797012279],"iteration":65,"passed_time":0.1898728893,"remaining_time":2.68698907},
{"learn":[5.768685095],"iteration":66,"passed_time":0.1905908248,"remaining_time":2.654048351},
{"learn":[5.755484587],"iteration":67,"passed_time":0.1910232821,"remaining_time":2.618142631},
{"learn":[5.731887055],"iteration":68,"passed_time":0.1917595751,"remaining_time":2.587364702},
{"learn":[5.707148487],"iteration":69,"passed_time":0.1924389629,"remaining_time":2.556689078},
{"learn":[5.685365039],"iteration":70,"passed_time":0.193200744,"remaining_time":2.527936496},
{"learn":[5.663541834],"iteration":71,"passed_time":0.1939126205,"remaining_time":2.499318219},
{"learn":[5.638108797],"iteration":72,"passed_time":0.1945908264,"remaining_time":2.471036933},
{"learn":[5.619204893],"iteration":73,"passed_time":0.1953171846,"remaining_time":2.444104228},
{"learn":[5.598472793],"iteration":74,"passed_time":0.196019697,"remaining_time":2.417576263},
{"learn":[5.577007075],"iteration":75,"passed_time":0.1967432809,"remaining_time":2.3919841},
{"learn":[5.562637084],"iteration":76,"passed_time":0.1974292886,"remaining_time":2.366587446},
{"learn":[5.54729991],"iteration":77,"passed_time":0.1981390218,"remaining_time":2.342104848},
{"learn":[5.530737623],"iteration":78,"passed_time":0.1988391206,"remaining_time":2.318111773},
{"learn":[5.513704873],"iteration":79,"passed_time":0.1995494447,"remaining_time":2.294818614},
{"learn":[5.501575529],"iteration":80,"passed_time":0.2001848466,"remaining_time":2.271233012},
{"learn":[5.484080734],"iteration":81,"passed_time":0.2008799879,"remaining_time":2.248875962},
{"learn":[5.472178894],"iteration":82,"passed_time":0.2015824803,"remaining_time":2.227122101},
{"learn":[5.458923342],"iteration":83,"passed_time":0.2022695295,"remaining_time":2.20570106},
{"learn":[5.451382371],"iteration":84,"passed_time":0.2027410158,"remaining_time":2.182447406},
{"learn":[5.441410748],"iteration":85,"passed_time":0.2033924317,"remaining_time":2.161635844},
{"learn":[5.434047468],"iteration":86,"passed_time":0.2038362866,"remaining_time":2.139109536},
{"learn":[5.422107497],"iteration":87,"passed_time":0.2044967159,"remaining_time":2.119329602},
{"learn":[5.40731265],"iteration":88,"passed_time":0.2051866996,"remaining_time":2.100281835},
{"learn":[5.396360181],"iteration":89,"passed_time":0.2059426615,"remaining_time":2.082309133},
{"learn":[5.383793239],"iteration":90,"passed_time":0.2066917837,"remaining_time":2.064646499},
{"learn":[5.369605034],"iteration":91,"passed_time":0.2073845114,"remaining_time":2.046794961},
{"learn":[5.357467333],"iteration":92,"passed_time":0.2080513905,"remaining_time":2.029060335},
{"learn":[5.341109968],"iteration":93,"passed_time":0.2087534722,"remaining_time":2.012028147},
{"learn":[5.330529276],"iteration":94,"passed_time":0.2094464804,"remaining_time":1.995253313},
{"learn":[5.319862075],"iteration":95,"passed_time":0.2101322677,"remaining_time":1.978745521},
{"learn":[5.313052243],"iteration":96,"passed_time":0.2108162724,"remaining_time":1.962547361},
{"learn":[5.299677207],"iteration":97,"passed_time":0.2115103221,"remaining_time":1.946758271},
{"learn":[5.287546698],"iteration":98,"passed_time":0.2122226692,"remaining_time":1.931440656},
{"learn":[5.279803754],"iteration":99,"passed_time":0.2128878657,"remaining_time":1.915990792},
{"learn":[5.272254612],"iteration":100,"passed_time":0.2136045594,"remaining_time":1.901292068},
{"learn":[5.268813888],"iteration":101,"passed_time":0.2139853398,"remaining_time":1.883910149},
{"learn":[5.258113767],"iteration":102,"passed_time":0.2146617631,"remaining_time":1.869433024},
{"learn":[5.251018576],"iteration":103,"passed_time":0.2153808003,"remaining_time":1.855588433},
{"learn":[5.24171237],"iteration":104,"passed_time":0.2160698826,"remaining_time":1.841738523},
{"learn":[5.233984943],"iteration":105,"passed_time":0.2167424401,"remaining_time":1.827997561},
{"learn":[5.226240449],"iteration":106,"passed_time":0.2174701402,"remaining_time":1.814961077},
{"learn":[5.220541644],"iteration":107,"passed_time":0.2181546356,"remaining_time":1.801795694},
{"learn":[5.211712096],"iteration":108,"passed_time":0.2188601325,"remaining_time":1.789030991},
{"learn":[5.203388597],"iteration":109,"passed_time":0.2195619338,"remaining_time":1.776455646},
{"learn":[5.196026544],"iteration":110,"passed_time":0.2202500847,"remaining_time":1.763984913},
{"learn":[5.188716772],"iteration":111,"passed_time":0.2209775345,"remaining_time":1.752036166},
{"learn":[5.182163132],"iteration":112,"passed_time":0.2216903623,"remaining_time":1.740171251},
{"learn":[5.17764747],"iteration":113,"passed_time":0.2223783229,"remaining_time":1.72830872},
{"learn":[5.170548056],"iteration":114,"passed_time":0.2230355475,"remaining_time":1.716403996},
{"learn":[5.165901827],"iteration":115,"passed_time":0.2236358567,"remaining_time":1.70425946},
{"learn":[5.160333668],"iteration":116,"passed_time":0.2242710183,"remaining_time":1.692575292},
{"learn":[5.148953243],"iteration":117,"passed_time":0.22494641,"remaining_time":1.681379099},
{"learn":[5.144729126],"iteration":118,"passed_time":0.2255049467,"remaining_time":1.669494606},
{"learn":[5.139939946],"iteration":119,"passed_time":0.2261945097,"remaining_time":1.658759738},
{"learn":[5.132898872],"iteration":120,"passed_time":0.226897573,"remaining_time":1.64828898},
{"learn":[5.129073077],"iteration":121,"passed_time":0.2276039311,"remaining_time":1.638002062},
{"learn":[5.127123916],"iteration":122,"passed_time":0.2279697892,"remaining_time":1.625443131},
{"learn":[5.121282057],"iteration":123,"passed_time":0.2286182206,"remaining_time":1.615077107},
{"learn":[5.114489821],"iteration":124,"passed_time":0.2292987,"remaining_time":1.6050909},
{"learn":[5.107777291],"iteration":125,"passed_time":0.229992269,"remaining_time":1.595343199},
{"learn":[5.103518754],"iteration":126,"passed_time":0.230668492,"remaining_time":1.585618846},
{"learn":[5.101133351],"iteration":127,"passed_time":0.2311222517,"remaining_time":1.57452034},
{"learn":[5.096462705],"iteration":128,"passed_time":0.2318007682,"remaining_time":1.565104412},
{"learn":[5.08562082],"iteration":129,"passed_time":0.2324984333,"remaining_time":1.555951054},
{"learn":[5.080483682],"iteration":130,"passed_time":0.233221146,"remaining_time":1.547092945},
{"learn":[5.07437499],"iteration":131,"passed_time":0.2339484255,"remaining_time":1.538388131},
{"learn":[5.070683732],"iteration":132,"passed_time":0.2346527606,"remaining_time":1.52965371},
{"learn":[5.06432037],"iteration":133,"passed_time":0.2353457487,"remaining_time":1.520965809},
{"learn":[5.057436484],"iteration":134,"passed_time":0.2361998582,"remaining_time":1.513428721},
{"learn":[5.053254656],"iteration":135,"passed_time":0.2369438934,"remaining_time":1.505290617},
{"learn":[5.04801663],"iteration":136,"passed_time":0.2376463457,"remaining_time":1.496998513},
{"learn":[5.045680836],"iteration":137,"passed_time":0.2382135454,"remaining_time":1.487971566},
{"learn":[5.041857933],"iteration":138,"passed_time":0.2388880859,"remaining_time":1.479731237},
{"learn":[5.035264888],"iteration":139,"passed_time":0.2396016348,"remaining_time":1.471838614},
{"learn":[5.028771948],"iteration":140,"passed_time":0.24030603,"remaining_time":1.463992055},
{"learn":[5.024912247],"iteration":141,"passed_time":0.2410213616,"remaining_time":1.456312171},
{"learn":[5.02239068],"iteration":142,"passed_time":0.2416982957,"remaining_time":1.448499576},
{"learn":[5.017110572],"iteration":143,"passed_time":0.2423807881,"remaining_time":1.440819129},
{"learn":[5.010707886],"iteration":144,"passed_time":0.243108328,"remaining_time":1.433500831},
{"learn":[5.004389868],"iteration":145,"passed_time":0.2438160482,"remaining_time":1.426156885},
{"learn":[4.997628683],"iteration":146,"passed_time":0.2445202932,"remaining_time":1.418883062},
{"learn":[4.991497851],"iteration":147,"passed_time":0.245206421,"remaining_time":1.411593721},
{"learn":[4.988345253],"iteration":148,"passed_time":0.2459098548,"remaining_time":1.404491855},
{"learn":[4.98460423],"iteration":149,"passed_time":0.2465850163,"remaining_time":1.397315092},
{"learn":[4.982441783],"iteration":150,"passed_time":0.2473051651,"remaining_time":1.390477385},
{"learn":[4.977461771],"iteration":151,"passed_time":0.24798934,"remaining_time":1.383519476},
{"learn":[4.973601586],"iteration":152,"passed_time":0.2487012064,"remaining_time":1.376796875},
{"learn":[4.968328804],"iteration":153,"passed_time":0.2494102386,"remaining_time":1.370136765},
{"learn":[4.9640736],"iteration":154,"passed_time":0.2501233569,"remaining_time":1.36357572},
{"learn":[4.960865882],"iteration":155,"passed_time":0.2508980173,"remaining_time":1.357422607},
{"learn":[4.957014156],"iteration":156,"passed_time":0.2516226028,"remaining_time":1.351069135},
{"learn":[4.952244852],"iteration":157,"passed_time":0.2522760918,"remaining_time":1.344408033},
{"learn":[4.949695675],"iteration":158,"passed_time":0.2529880583,"remaining_time":1.338131805},
{"learn":[4.946584698],"iteration":159,"passed_time":0.2536283475,"remaining_time":1.331548824},
{"learn":[4.940192834],"iteration":160,"passed_time":0.2542919015,"remaining_time":1.325160903},
{"learn":[4.936727994],"iteration":161,"passed_time":0.2549809037,"remaining_time":1.318975292},
{"learn":[4.932342063],"iteration":162,"passed_time":0.2556544427,"remaining_time":1.312777721},
{"learn":[4.925830838],"iteration":163,"passed_time":0.2563631243,"remaining_time":1.306826658},
{"learn":[4.922571773],"iteration":164,"passed_time":0.2570496628,"remaining_time":1.300827081},
{"learn":[4.918395814],"iteration":165,"passed_time":0.2577495012,"remaining_time":1.294958337},
{"learn":[4.911142452],"iteration":166,"passed_time":0.2584302109,"remaining_time":1.289056082},
{"learn":[4.908276131],"iteration":167,"passed_time":0.2590943959,"remaining_time":1.283134151},
{"learn":[4.904584645],"iteration":168,"passed_time":0.2598508792,"remaining_time":1.277728287},
{"learn":[4.89795517],"iteration":169,"passed_time":0.2605419244,"remaining_time":1.272057631},
{"learn":[4.895556491],"iteration":170,"passed_time":0.2612443767,"remaining_time":1.266500516},
{"learn":[4.890591233],"iteration":171,"passed_time":0.2619368741,"remaining_time":1.260951929},
{"learn":[4.884629277],"iteration":172,"passed_time":0.2626191562,"remaining_time":1.255410648},
{"learn":[4.880550786],"iteration":173,"passed_time":0.2633190947,"remaining_time":1.250009036},
{"learn":[4.876384842],"iteration":174,"passed_time":0.2639852326,"remaining_time":1.244501811},
{"learn":[4.872638238],"iteration":175,"passed_time":0.2646798226,"remaining_time":1.239182806},
{"learn":[4.869137118],"iteration":176,"passed_time":0.2653788898,"remaining_time":1.233936872},
{"learn":[4.863587157],"iteration":177,"passed_time":0.2661733405,"remaining_time":1.229182505},
{"learn":[4.858028614],"iteration":178,"passed_time":0.2669539699,"remaining_time":1.224408991},
{"learn":[4.853838176],"iteration":179,"passed_time":0.2676358314,"remaining_time":1.219229899},
{"learn":[4.853462329],"iteration":180,"passed_time":0.2680017195,"remaining_time":1.212670764},
{"learn":[4.851573196],"iteration":181,"passed_time":0.2686807567,"remaining_time":1.207587137},
{"learn":[4.848442087],"iteration":182,"passed_time":0.2693966792,"remaining_time":1.202716322},
{"learn":[4.845547104],"iteration":183,"passed_time":0.270084089,"remaining_time":1.197764221},
{"learn":[4.839868817],"iteration":184,"passed_time":0.2707614437,"remaining_time":1.192813928},
{"learn":[4.836336958],"iteration":185,"passed_time":0.2714234755,"remaining_time":1.187842522},
{"learn":[4.831124789],"iteration":186,"passed_time":0.2721532787,"remaining_time":1.183211848},
{"learn":[4.827407333],"iteration":187,"passed_time":0.2728271783,"remaining_time":1.178381217},
{"learn":[4.824088918],"iteration":188,"passed_time":0.273547918,"remaining_time":1.173795563},
{"learn":[4.820934539],"iteration":189,"passed_time":0.2742163093,"remaining_time":1.169027424},
{"learn":[4.816975227],"iteration":190,"passed_time":0.2748918412,"remaining_time":1.164332458},
{"learn":[4.812340486],"iteration":191,"passed_time":0.2755736626,"remaining_time":1.15970583},
{"learn":[4.806402747],"iteration":192,"passed_time":0.2762600609,"remaining_time":1.155139218},
{"learn":[4.801521788],"iteration":193,"passed_time":0.2769562138,"remaining_time":1.150653136},
{"learn":[4.797601172],"iteration":194,"passed_time":0.2776274193,"remaining_time":1.146102936},
{"learn":[4.792694629],"iteration":195,"passed_time":0.2783089603,"remaining_time":1.141634714},
{"learn":[4.789794613],"iteration":196,"passed_time":0.2790307816,"remaining_time":1.137369125},
{"learn":[4.785367055],"iteration":197,"passed_time":0.2797066541,"remaining_time":1.132953215},
{"learn":[4.780376856],"iteration":198,"passed_time":0.2803926217,"remaining_time":1.128615527},
{"learn":[4.776691261],"iteration":199,"passed_time":0.2810955541,"remaining_time":1.124382217},
{"learn":[4.773470753],"iteration":200,"passed_time":0.2817774256,"remaining_time":1.120100314},
{"learn":[4.77207327],"iteration":201,"passed_time":0.2825062374,"remaining_time":1.116039492},
{"learn":[4.767347177],"iteration":202,"passed_time":0.2831869872,"remaining_time":1.111822802},
{"learn":[4.763983068],"iteration":203,"passed_time":0.2838710219,"remaining_time":1.107653595},
{"learn":[4.761588849],"iteration":204,"passed_time":0.2845562785,"remaining_time":1.103523129},
{"learn":[4.758558086],"iteration":205,"passed_time":0.2852468029,"remaining_time":1.099446415},
{"learn":[4.753678804],"iteration":206,"passed_time":0.2859083239,"remaining_time":1.095291309},
{"learn":[4.746510889],"iteration":207,"passed_time":0.2866145018,"remaining_time":1.091339834},
{"learn":[4.744840601],"iteration":208,"passed_time":0.2873230733,"remaining_time":1.087428473},
{"learn":[4.741702222],"iteration":209,"passed_time":0.2880307334,"remaining_time":1.083544187},
{"learn":[4.739352853],"iteration":210,"passed_time":0.2887165207,"remaining_time":1.079608222},
{"learn":[4.735539287],"iteration":211,"passed_time":0.2893945264,"remaining_time":1.075673994},
{"learn":[4.730726751],"iteration":212,"passed_time":0.2900915306,"remaining_time":1.071840538},
{"learn":[4.726416092],"iteration":213,"passed_time":0.2907826058,"remaining_time":1.068014618},
{"learn":[4.721293082],"iteration":214,"passed_time":0.2914785984,"remaining_time":1.064235813},
{"learn":[4.718443695],"iteration":215,"passed_time":0.2921891529,"remaining_time":1.060538407},
{"learn":[4.711627962],"iteration":216,"passed_time":0.2928608892,"remaining_time":1.056728462},
{"learn":[4.709790764],"iteration":217,"passed_time":0.2935538973,"remaining_time":1.053023613},
{"learn":[4.706913073],"iteration":218,"passed_time":0.2942044619,"remaining_time":1.049194908},
{"learn":[4.703846389],"iteration":219,"passed_time":0.2948718417,"remaining_time":1.045454711},
{"learn":[4.701001135],"iteration":220,"passed_time":0.2955695374,"remaining_time":1.041849184},
{"learn":[4.700380864],"iteration":221,"passed_time":0.2962146939,"remaining_time":1.038085729},
{"learn":[4.695837486],"iteration":222,"passed_time":0.2969223941,"remaining_time":1.034568162},
{"learn":[4.691242996],"iteration":223,"passed_time":0.2975917768,"remaining_time":1.030942941},
{"learn":[4.690284609],"iteration":224,"passed_time":0.298268761,"remaining_time":1.027370177},
{"learn":[4.68827119],"iteration":225,"passed_time":0.2989678783,"remaining_time":1.02389884},
{"learn":[4.686922425],"iteration":226,"passed_time":0.2996416076,"remaining_time":1.020365474},
{"learn":[4.686085874],"iteration":227,"passed_time":0.300315417,"remaining_time":1.016857465},
{"learn":[4.683230741],"iteration":228,"passed_time":0.3010171682,"remaining_time":1.013468283},
{"learn":[4.6773487],"iteration":229,"passed_time":0.3017449285,"remaining_time":1.010189543},
{"learn":[4.671462906],"iteration":230,"passed_time":0.3024265295,"remaining_time":1.006779226},
{"learn":[4.664799601],"iteration":231,"passed_time":0.303151786,"remaining_time":1.003536947},
{"learn":[4.660979386],"iteration":232,"passed_time":0.3038258257,"remaining_time":1.000147675},
{"learn":[4.656281279],"iteration":233,"passed_time":0.3045568609,"remaining_time":0.9969681856},
{"learn":[4.651997094],"iteration":234,"passed_time":0.3053250216,"remaining_time":0.9939303895},
{"learn":[4.650151977],"iteration":235,"passed_time":0.3060654208,"remaining_time":0.9908219554},
{"learn":[4.648478046],"iteration":236,"passed_time":0.3067519993,"remaining_time":0.987560234},
{"learn":[4.646364602],"iteration":237,"passed_time":0.307510475,"remaining_time":0.9845503442},
{"learn":[4.642635873],"iteration":238,"passed_time":0.3081814201,"remaining_time":0.9812805886},
{"learn":[4.640860821],"iteration":239,"passed_time":0.3089354196,"remaining_time":0.9782954954},
{"learn":[4.639446822],"iteration":240,"passed_time":0.309696019,"remaining_time":0.9753497031},
{"learn":[4.637120072],"iteration":241,"passed_time":0.3103891874,"remaining_time":0.9722107606},
{"learn":[4.633769267],"iteration":242,"passed_time":0.3110693363,"remaining_time":0.9690513893},
{"learn":[4.630491517],"iteration":243,"passed_time":0.3117648683,"remaining_time":0.9659600017},
{"learn":[4.627813333],"iteration":244,"passed_time":0.3124507357,"remaining_time":0.9628583897},
{"learn":[4.622496304],"iteration":245,"passed_time":0.3131449557,"remaining_time":0.9598020187},
{"learn":[4.618979301],"iteration":246,"passed_time":0.3138376534,"remaining_time":0.9567601336},
{"learn":[4.616563458],"iteration":247,"passed_time":0.31449628,"remaining_time":0.9536338814},
{"learn":[4.614759385],"iteration":248,"passed_time":0.3151587024,"remaining_time":0.9505388976},
{"learn":[4.61251363],"iteration":249,"passed_time":0.3157669536,"remaining_time":0.9473008607},
{"learn":[4.608796693],"iteration":250,"passed_time":0.3164540228,"remaining_time":0.9443189765},
{"learn":[4.60847774],"iteration":251,"passed_time":0.3171359945,"remaining_time":0.941340174},
{"learn":[4.605195659],"iteration":252,"passed_time":0.3177937398,"remaining_time":0.9383079985},
{"learn":[4.60103766],"iteration":253,"passed_time":0.3184906638,"remaining_time":0.9354095875},
{"learn":[4.599325598],"iteration":254,"passed_time":0.3191612083,"remaining_time":0.9324513734},
{"learn":[4.597012808],"iteration":255,"passed_time":0.3198547673,"remaining_time":0.9295779175},
{"learn":[4.594161533],"iteration":256,"passed_time":0.3205295281,"remaining_time":0.9266670794},
{"learn":[4.592197259],"iteration":257,"passed_time":0.3211998323,"remaining_time":0.923760758},
{"learn":[4.58952828],"iteration":258,"passed_time":0.3219431953,"remaining_time":0.9210807249},
{"learn":[4.585816572],"iteration":259,"passed_time":0.3231676201,"remaining_time":0.919784765},
{"learn":[4.582934052],"iteration":260,"passed_time":0.3239983641,"remaining_time":0.9173746783},
{"learn":[4.582234842],"iteration":261,"passed_time":0.3247307813,"remaining_time":0.9146996816},
{"learn":[4.57571562],"iteration":262,"passed_time":0.3254644403,"remaining_time":0.9120429373},
{"learn":[4.571197349],"iteration":263,"passed_time":0.3261726212,"remaining_time":0.9093297319},
{"learn":[4.56723703],"iteration":264,"passed_time":0.3268719488,"remaining_time":0.9066071034},
{"learn":[4.560335567],"iteration":265,"passed_time":0.3275635148,"remaining_time":0.9038782703},
{"learn":[4.554709345],"iteration":266,"passed_time":0.3282355616,"remaining_time":0.9011111111},
{"learn":[4.552806306],"iteration":267,"passed_time":0.3289394461,"remaining_time":0.8984465467},
{"learn":[4.550766241],"iteration":268,"passed_time":0.3295887187,"remaining_time":0.8956481538},
{"learn":[4.549216045],"iteration":269,"passed_time":0.3302634395,"remaining_time":0.8929344845},
{"learn":[4.547687452],"iteration":270,"passed_time":0.330929317,"remaining_time":0.8902120741},
{"learn":[4.545642435],"iteration":271,"passed_time":0.3315660308,"remaining_time":0.8874267295},
{"learn":[4.543930359],"iteration":272,"passed_time":0.3322247676,"remaining_time":0.8847157731},
{"learn":[4.541029943],"iteration":273,"passed_time":0.3329433441,"remaining_time":0.8821783496},
{"learn":[4.537781449],"iteration":274,"passed_time":0.3336218004,"remaining_time":0.879548383},
{"learn":[4.53066128],"iteration":275,"passed_time":0.3344177728,"remaining_time":0.8772408244},
{"learn":[4.526763956],"iteration":276,"passed_time":0.3351063143,"remaining_time":0.8746637735},
{"learn":[4.522036004],"iteration":277,"passed_time":0.3357994627,"remaining_time":0.8721122736},
{"learn":[4.515307629],"iteration":278,"passed_time":0.336497919,"remaining_time":0.8695878122},
{"learn":[4.51109143],"iteration":279,"passed_time":0.3371674019,"remaining_time":0.8670018907},
{"learn":[4.508233494],"iteration":280,"passed_time":0.3378633745,"remaining_time":0.8644973889},
{"learn":[4.502555629],"iteration":281,"passed_time":0.3385582755,"remaining_time":0.8620029852},
{"learn":[4.500081355],"iteration":282,"passed_time":0.3392604574,"remaining_time":0.8595397455},
{"learn":[4.495281743],"iteration":283,"passed_time":0.3399247025,"remaining_time":0.856993264},
{"learn":[4.492138869],"iteration":284,"passed_time":0.3407005147,"remaining_time":0.8547398878},
{"learn":[4.491708261],"iteration":285,"passed_time":0.3414101077,"remaining_time":0.8523315276},
{"learn":[4.489398865],"iteration":286,"passed_time":0.3420738921,"remaining_time":0.8498212023},
{"learn":[4.485796373],"iteration":287,"passed_time":0.3427690034,"remaining_time":0.8474011473},
{"learn":[4.479542205],"iteration":288,"passed_time":0.3434524773,"remaining_time":0.8449643991},
{"learn":[4.475986993],"iteration":289,"passed_time":0.3441373032,"remaining_time":0.8425430526},
{"learn":[4.468661855],"iteration":290,"passed_time":0.3448258847,"remaining_time":0.8401427912},
{"learn":[4.463785664],"iteration":291,"passed_time":0.3455312814,"remaining_time":0.8377950248},
{"learn":[4.460445831],"iteration":292,"passed_time":0.3462082656,"remaining_time":0.8353899104},
{"learn":[4.45692492],"iteration":293,"passed_time":0.3468893058,"remaining_time":0.8330062922},
{"learn":[4.454031688],"iteration":294,"passed_time":0.3475985082,"remaining_time":0.8307015197},
{"learn":[4.451672391],"iteration":295,"passed_time":0.3482873501,"remaining_time":0.828359103},
{"learn":[4.45031553],"iteration":296,"passed_time":0.3489398376,"remaining_time":0.8259417705},
{"learn":[4.446782666],"iteration":297,"passed_time":0.3496027807,"remaining_time":0.823560913},
{"learn":[4.444369689],"iteration":298,"passed_time":0.3502487785,"remaining_time":0.8211518184},
{"learn":[4.44411683],"iteration":299,"passed_time":0.3508876555,"remaining_time":0.8187378629},
{"learn":[4.440876943],"iteration":300,"passed_time":0.3515830773,"remaining_time":0.8164670134},
{"learn":[4.439336453],"iteration":301,"passed_time":0.3522828055,"remaining_time":0.8142165505},
{"learn":[4.436666901],"iteration":302,"passed_time":0.3529916574,"remaining_time":0.811997311},
{"learn":[4.433043336],"iteration":303,"passed_time":0.3537125474,"remaining_time":0.8098155689},
{"learn":[4.431419305],"iteration":304,"passed_time":0.3543883197,"remaining_time":0.8075405973},
{"learn":[4.428859646],"iteration":305,"passed_time":0.355090101,"remaining_time":0.8053350657},
{"learn":[4.424552441],"iteration":306,"passed_time":0.3558120931,"remaining_time":0.8031849529},
{"learn":[4.422706391],"iteration":307,"passed_time":0.3565506189,"remaining_time":0.8010812607},
{"learn":[4.421427994],"iteration":308,"passed_time":0.3572554854,"remaining_time":0.798911134},
{"learn":[4.418733158],"iteration":309,"passed_time":0.3578997005,"remaining_time":0.7966154623},
{"learn":[4.415656941],"iteration":310,"passed_time":0.3585824232,"remaining_time":0.7944157222},
{"learn":[4.410747417],"iteration":311,"passed_time":0.3592570438,"remaining_time":0.7922078402},
{"learn":[4.408126521],"iteration":312,"passed_time":0.3599438126,"remaining_time":0.7900364194},
{"learn":[4.407843853],"iteration":313,"passed_time":0.3606026296,"remaining_time":0.7878133882},
{"learn":[4.405219398],"iteration":314,"passed_time":0.3612947364,"remaining_time":0.7856726807},
{"learn":[4.402708465],"iteration":315,"passed_time":0.3619701782,"remaining_time":0.7835050693},
{"learn":[4.40104971],"iteration":316,"passed_time":0.3627019144,"remaining_time":0.7814681626},
{"learn":[4.400830038],"iteration":317,"passed_time":0.3633916977,"remaining_time":0.7793494901},
{"learn":[4.39784288],"iteration":318,"passed_time":0.3640442954,"remaining_time":0.7771603923},
{"learn":[4.393741845],"iteration":319,"passed_time":0.3648572332,"remaining_time":0.7753216205},
{"learn":[4.393425936],"iteration":320,"passed_time":0.3655310125,"remaining_time":0.7731948832},
{"learn":[4.390505974],"iteration":321,"passed_time":0.3662367793,"remaining_time":0.7711445228},
{"learn":[4.390305136],"iteration":322,"passed_time":0.3668677545,"remaining_time":0.7689457269},
{"learn":[4.38568203],"iteration":323,"passed_time":0.3676212332,"remaining_time":0.7670122027},
{"learn":[4.383057135],"iteration":324,"passed_time":0.3682833451,"remaining_time":0.7648961783},
{"learn":[4.380662684],"iteration":325,"passed_time":0.3690318069,"remaining_time":0.7629676008},
{"learn":[4.37805727],"iteration":326,"passed_time":0.3697435526,"remaining_time":0.7609706755},
{"learn":[4.373708319],"iteration":327,"passed_time":0.3704866758,"remaining_time":0.7590458724},
{"learn":[4.36887921],"iteration":328,"passed_time":0.3712361491,"remaining_time":0.7571412038},
{"learn":[4.367895929],"iteration":329,"passed_time":0.3719672838,"remaining_time":0.7552063035},
{"learn":[4.362140573],"iteration":330,"passed_time":0.3726665013,"remaining_time":0.7532141673},
{"learn":[4.361931924],"iteration":331,"passed_time":0.3734181779,"remaining_time":0.75133537},
{"learn":[4.359656377],"iteration":332,"passed_time":0.374198567,"remaining_time":0.7495208533},
{"learn":[4.354281355],"iteration":333,"passed_time":0.3748934379,"remaining_time":0.7475420049},
{"learn":[4.348589447],"iteration":334,"passed_time":0.3756284785,"remaining_time":0.7456505617},
{"learn":[4.346355698],"iteration":335,"passed_time":0.3763581716,"remaining_time":0.7437554343},
{"learn":[4.343894047],"iteration":336,"passed_time":0.3770881056,"remaining_time":0.7418676974},
{"learn":[4.341561356],"iteration":337,"passed_time":0.3778117697,"remaining_time":0.7399745312},
{"learn":[4.338869061],"iteration":338,"passed_time":0.3786312779,"remaining_time":0.7382751466},
{"learn":[4.333720063],"iteration":339,"passed_time":0.3793237853,"remaining_time":0.7363344068},
{"learn":[4.330892223],"iteration":340,"passed_time":0.3799966633,"remaining_time":0.7343630532},
{"learn":[4.328311474],"iteration":341,"passed_time":0.3806892709,"remaining_time":0.7324372522},
{"learn":[4.324580133],"iteration":342,"passed_time":0.3814725142,"remaining_time":0.7306922503},
{"learn":[4.323354432],"iteration":343,"passed_time":0.3822074652,"remaining_time":0.7288607476},
{"learn":[4.323159553],"iteration":344,"passed_time":0.3828468831,"remaining_time":0.7268542273},
{"learn":[4.318639682],"iteration":345,"passed_time":0.3835659509,"remaining_time":0.7250061614},
{"learn":[4.312712208],"iteration":346,"passed_time":0.3842782179,"remaining_time":0.7231518048},
{"learn":[4.311461062],"iteration":347,"passed_time":0.3849706657,"remaining_time":0.7212668795},
{"learn":[4.311178356],"iteration":348,"passed_time":0.3856632533,"remaining_time":0.7193890484},
{"learn":[4.311102505],"iteration":349,"passed_time":0.3864083194,"remaining_time":0.7176154503},
{"learn":[4.310232308],"iteration":350,"passed_time":0.3872064556,"remaining_time":0.7159458396},
{"learn":[4.305128197],"iteration":351,"passed_time":0.3879192034,"remaining_time":0.714123988},
{"learn":[4.304595496],"iteration":352,"passed_time":0.388644269,"remaining_time":0.7123309972},
{"learn":[4.3004992],"iteration":353,"passed_time":0.3893958054,"remaining_time":0.7105923454},
{"learn":[4.297581524],"iteration":354,"passed_time":0.3901141715,"remaining_time":0.7087989877},
{"learn":[4.297355825],"iteration":355,"passed_time":0.3908613102,"remaining_time":0.7070637185},
{"learn":[4.295758715],"iteration":356,"passed_time":0.3915553605,"remaining_time":0.7052383664},
{"learn":[4.292500657],"iteration":357,"passed_time":0.3922794953,"remaining_time":0.7034732848},
{"learn":[4.290797586],"iteration":358,"passed_time":0.392964842,"remaining_time":0.7016447457},
{"learn":[4.286410608],"iteration":359,"passed_time":0.3936452813,"remaining_time":0.6998138334},
{"learn":[4.280278245],"iteration":360,"passed_time":0.394317328,"remaining_time":0.6979744394},
{"learn":[4.279941283],"iteration":361,"passed_time":0.3949491746,"remaining_time":0.6960706447},
{"learn":[4.274426275],"iteration":362,"passed_time":0.3956515768,"remaining_time":0.6942976706},
{"learn":[4.273567658],"iteration":363,"passed_time":0.3963267182,"remaining_time":0.6924829472},
{"learn":[4.269488271],"iteration":364,"passed_time":0.3970168521,"remaining_time":0.6907005509},
{"learn":[4.266838205],"iteration":365,"passed_time":0.3976860946,"remaining_time":0.6888879344},
{"learn":[4.263456509],"iteration":366,"passed_time":0.3983683467,"remaining_time":0.6871039876},
{"learn":[4.260360204],"iteration":367,"passed_time":0.3990575291,"remaining_time":0.6853379304},
{"learn":[4.255120549],"iteration":368,"passed_time":0.3997998005,"remaining_time":0.6836684935},
{"learn":[4.252582211],"iteration":369,"passed_time":0.4004913064,"remaining_time":0.6819176298},
{"learn":[4.247857931],"iteration":370,"passed_time":0.4011753311,"remaining_time":0.6801597932},
{"learn":[4.245288911],"iteration":371,"passed_time":0.4018723152,"remaining_time":0.6784296074},
{"learn":[4.24048515],"iteration":372,"passed_time":0.4025739964,"remaining_time":0.6767128572},
{"learn":[4.2378365],"iteration":373,"passed_time":0.4032502995,"remaining_time":0.6749590575},
{"learn":[4.236751063],"iteration":374,"passed_time":0.4039524414,"remaining_time":0.6732540689},
{"learn":[4.233240093],"iteration":375,"passed_time":0.404663777,"remaining_time":0.6715696724},
{"learn":[4.230358421],"iteration":376,"passed_time":0.4053906659,"remaining_time":0.6699161402},
{"learn":[4.225853583],"iteration":377,"passed_time":0.4061024628,"remaining_time":0.6682426768},
{"learn":[4.224702126],"iteration":378,"passed_time":0.4067529873,"remaining_time":0.6664738921},
{"learn":[4.224361982],"iteration":379,"passed_time":0.4074251843,"remaining_time":0.6647463533},
{"learn":[4.223787954],"iteration":380,"passed_time":0.4080917328,"remaining_time":0.6630151774},
{"learn":[4.22144054],"iteration":381,"passed_time":0.40875739,"remaining_time":0.6612881335},
{"learn":[4.217739335],"iteration":382,"passed_time":0.4094319905,"remaining_time":0.6595810396},
{"learn":[4.215611665],"iteration":383,"passed_time":0.410116486,"remaining_time":0.6578951962},
{"learn":[4.210236863],"iteration":384,"passed_time":0.4108144315,"remaining_time":0.6562360399},
{"learn":[4.208454294],"iteration":385,"passed_time":0.4114649059,"remaining_time":0.654506353},
{"learn":[4.207446501],"iteration":386,"passed_time":0.4121061265,"remaining_time":0.6527675854},
{"learn":[4.204985442],"iteration":387,"passed_time":0.4127824096,"remaining_time":0.6510897801},
{"learn":[4.202796622],"iteration":388,"passed_time":0.4134694889,"remaining_time":0.6494340816},
{"learn":[4.199774004],"iteration":389,"passed_time":0.4141568186,"remaining_time":0.6477837419},
{"learn":[4.199458358],"iteration":390,"passed_time":0.4148380886,"remaining_time":0.6461288899},
{"learn":[4.19751254],"iteration":391,"passed_time":0.4155557537,"remaining_time":0.6445354547},
{"learn":[4.195201346],"iteration":392,"passed_time":0.4162502641,"remaining_time":0.6429107132},
{"learn":[4.190593508],"iteration":393,"passed_time":0.4169590859,"remaining_time":0.6413127058},
{"learn":[4.187212054],"iteration":394,"passed_time":0.4176378928,"remaining_time":0.6396732283},
{"learn":[4.184984466],"iteration":395,"passed_time":0.4183127438,"remaining_time":0.6380325688},
{"learn":[4.182832144],"iteration":396,"passed_time":0.4190117209,"remaining_time":0.6364334199},
{"learn":[4.179752812],"iteration":397,"passed_time":0.4197588101,"remaining_time":0.634911567},
{"learn":[4.17878934],"iteration":398,"passed_time":0.4204768863,"remaining_time":0.6333498965},
{"learn":[4.174548229],"iteration":399,"passed_time":0.4211554729,"remaining_time":0.6317332093},
{"learn":[4.168872556],"iteration":400,"passed_time":0.4218545201,"remaining_time":0.6301517644},
{"learn":[4.163926494],"iteration":401,"passed_time":0.422543382,"remaining_time":0.6285595584},
{"learn":[4.159485076],"iteration":402,"passed_time":0.4232557893,"remaining_time":0.6270067151},
{"learn":[4.155926102],"iteration":403,"passed_time":0.4239372101,"remaining_time":0.6254123198},
{"learn":[4.153540115],"iteration":404,"passed_time":0.4246181702,"remaining_time":0.6238217562},
{"learn":[4.150983044],"iteration":405,"passed_time":0.4253005324,"remaining_time":0.6222377247},
{"learn":[4.146539132],"iteration":406,"passed_time":0.4259944319,"remaining_time":0.6206749339},
{"learn":[4.144869174],"iteration":407,"passed_time":0.4266952718,"remaining_time":0.6191264728},
{"learn":[4.142825962],"iteration":408,"passed_time":0.4273748298,"remaining_time":0.6175514044},
{"learn":[4.142467378],"iteration":409,"passed_time":0.4280251941,"remaining_time":0.6159386939},
{"learn":[4.141800768],"iteration":410,"passed_time":0.4286677466,"remaining_time":0.6143194715},
{"learn":[4.140107084],"iteration":411,"passed_time":0.4293207248,"remaining_time":0.6127198694},
{"learn":[4.136243196],"iteration":412,"passed_time":0.4301101168,"remaining_time":0.6113187375},
{"learn":[4.133618439],"iteration":413,"passed_time":0.4308111971,"remaining_time":0.6097955591},
{"learn":[4.131053025],"iteration":414,"passed_time":0.4314867791,"remaining_time":0.6082403995},
{"learn":[4.128379975],"iteration":415,"passed_time":0.4321633126,"remaining_time":0.6066908042},
{"learn":[4.127068571],"iteration":416,"passed_time":0.4328503218,"remaining_time":0.6051600422},
{"learn":[4.125969877],"iteration":417,"passed_time":0.4335464146,"remaining_time":0.6036459648},
{"learn":[4.123893633],"iteration":418,"passed_time":0.4342092976,"remaining_time":0.602089742},
{"learn":[4.119643722],"iteration":419,"passed_time":0.4350318799,"remaining_time":0.6007583103},
{"learn":[4.11465686],"iteration":420,"passed_time":0.4357646376,"remaining_time":0.5993057604},
{"learn":[4.111565986],"iteration":421,"passed_time":0.4364545411,"remaining_time":0.5977979259},
{"learn":[4.106322452],"iteration":422,"passed_time":0.4371319158,"remaining_time":0.5962768686},
{"learn":[4.104222175],"iteration":423,"passed_time":0.4378347487,"remaining_time":0.5947943756},
{"learn":[4.103008002],"iteration":424,"passed_time":0.4385356587,"remaining_time":0.59331295},
{"learn":[4.099176337],"iteration":425,"passed_time":0.4392647509,"remaining_time":0.591873162},
{"learn":[4.096525716],"iteration":426,"passed_time":0.4399561266,"remaining_time":0.5903860903},
{"learn":[4.094967724],"iteration":427,"passed_time":0.4406378579,"remaining_time":0.5888898475},
{"learn":[4.094683584],"iteration":428,"passed_time":0.4413202702,"remaining_time":0.5873983083},
{"learn":[4.091096563],"iteration":429,"passed_time":0.4419880005,"remaining_time":0.5858910704},
{"learn":[4.089178677],"iteration":430,"passed_time":0.4426790357,"remaining_time":0.5844184949},
{"learn":[4.085335077],"iteration":431,"passed_time":0.4433906517,"remaining_time":0.5829765976},
{"learn":[4.084852122],"iteration":432,"passed_time":0.4440774806,"remaining_time":0.5815056155},
{"learn":[4.080322952],"iteration":433,"passed_time":0.4447676946,"remaining_time":0.5800426616},
{"learn":[4.077449519],"iteration":434,"passed_time":0.4455639496,"remaining_time":0.578720992},
{"learn":[4.076568374],"iteration":435,"passed_time":0.4462138232,"remaining_time":0.5772123768},
{"learn":[4.076071793],"iteration":436,"passed_time":0.446859861,"remaining_time":0.5757027499},
{"learn":[4.075027644],"iteration":437,"passed_time":0.4475314671,"remaining_time":0.5742298733},
{"learn":[4.07020837],"iteration":438,"passed_time":0.4482184161,"remaining_time":0.5727802539},
{"learn":[4.06833694],"iteration":439,"passed_time":0.4488997168,"remaining_time":0.5713269123},
{"learn":[4.063936568],"iteration":440,"passed_time":0.4496138666,"remaining_time":0.5699187107},
{"learn":[4.061734926],"iteration":441,"passed_time":0.4504522047,"remaining_time":0.5686704304},
{"learn":[4.060815619],"iteration":442,"passed_time":0.4511514822,"remaining_time":0.5672491549},
{"learn":[4.056407489],"iteration":443,"passed_time":0.4518354969,"remaining_time":0.5658120187},
{"learn":[4.05238936],"iteration":444,"passed_time":0.4525089358,"remaining_time":0.5643650772},
{"learn":[4.049685254],"iteration":445,"passed_time":0.4532005218,"remaining_time":0.5629441459},
{"learn":[4.045162016],"iteration":446,"passed_time":0.4538832145,"remaining_time":0.5615154757},
{"learn":[4.042955482],"iteration":447,"passed_time":0.4545267085,"remaining_time":0.5600418373},
{"learn":[4.041467663],"iteration":448,"passed_time":0.4552009085,"remaining_time":0.5586095781},
{"learn":[4.038920476],"iteration":449,"passed_time":0.455937572,"remaining_time":0.5572570325},
{"learn":[4.036694383],"iteration":450,"passed_time":0.4566148667,"remaining_time":0.5558349485},
{"learn":[4.034999007],"iteration":451,"passed_time":0.4572998929,"remaining_time":0.5544255338},
{"learn":[4.031928018],"iteration":452,"passed_time":0.4579660808,"remaining_time":0.55299657},
{"learn":[4.028718143],"iteration":453,"passed_time":0.4586859086,"remaining_time":0.551635476},
{"learn":[4.027401978],"iteration":454,"passed_time":0.4594492427,"remaining_time":0.5503293127},
{"learn":[4.025930598],"iteration":455,"passed_time":0.4603600766,"remaining_time":0.5492014949},
{"learn":[4.021074523],"iteration":456,"passed_time":0.4611389935,"remaining_time":0.547917885},
{"learn":[4.020268486],"iteration":457,"passed_time":0.4618495679,"remaining_time":0.5465556022},
{"learn":[4.017986361],"iteration":458,"passed_time":0.4626554752,"remaining_time":0.5453085231},
{"learn":[4.014814804],"iteration":459,"passed_time":0.4634359644,"remaining_time":0.5440335235},
{"learn":[4.009704796],"iteration":460,"passed_time":0.4641370046,"remaining_time":0.5426677776},
{"learn":[4.008440457],"iteration":461,"passed_time":0.464927229,"remaining_time":0.5414087645},
{"learn":[4.004854849],"iteration":462,"passed_time":0.4657164808,"remaining_time":0.5401506483},
{"learn":[4.000898028],"iteration":463,"passed_time":0.4663911715,"remaining_time":0.5387622153},
{"learn":[3.996617985],"iteration":464,"passed_time":0.4671677849,"remaining_time":0.5374941181},
{"learn":[3.995443319],"iteration":465,"passed_time":0.4678832066,"remaining_time":0.5361580093},
{"learn":[3.990771995],"iteration":466,"passed_time":0.4686804309,"remaining_time":0.5349179222},
{"learn":[3.989249359],"iteration":467,"passed_time":0.4694572847,"remaining_time":0.5336565715},
{"learn":[3.986599538],"iteration":468,"passed_time":0.4702600873,"remaining_time":0.532426666},
{"learn":[3.985628919],"iteration":469,"passed_time":0.4710202661,"remaining_time":0.5311505128},
{"learn":[3.985086112],"iteration":470,"passed_time":0.471858923,"remaining_time":0.5299646927},
{"learn":[3.98466839],"iteration":471,"passed_time":0.4726382299,"remaining_time":0.5287139521},
{"learn":[3.984233894],"iteration":472,"passed_time":0.4733446982,"remaining_time":0.5273840506},
{"learn":[3.981855845],"iteration":473,"passed_time":0.4740233148,"remaining_time":0.5260258725},
{"learn":[3.978684264],"iteration":474,"passed_time":0.474875236,"remaining_time":0.524862103},
{"learn":[3.974361269],"iteration":475,"passed_time":0.4758378881,"remaining_time":0.5238215407},
{"learn":[3.972074049],"iteration":476,"passed_time":0.4765117075,"remaining_time":0.5224646185},
{"learn":[3.97191982],"iteration":477,"passed_time":0.4771463583,"remaining_time":0.5210677804},
{"learn":[3.969616848],"iteration":478,"passed_time":0.4778347695,"remaining_time":0.519732599},
{"learn":[3.968533527],"iteration":479,"passed_time":0.4785251037,"remaining_time":0.5184021957},
{"learn":[3.967568753],"iteration":480,"passed_time":0.479194847,"remaining_time":0.5170522362},
{"learn":[3.966232553],"iteration":481,"passed_time":0.4798827175,"remaining_time":0.5157245802},
{"learn":[3.961522393],"iteration":482,"passed_time":0.4805560962,"remaining_time":0.5143840616},
{"learn":[3.955829553],"iteration":483,"passed_time":0.481236826,"remaining_time":0.5130541368},
{"learn":[3.954248095],"iteration":484,"passed_time":0.4819049168,"remaining_time":0.5117134684},
{"learn":[3.951922606],"iteration":485,"passed_time":0.4826102334,"remaining_time":0.5104149382},
{"learn":[3.94978202],"iteration":486,"passed_time":0.4833079687,"remaining_time":0.5091108582},
{"learn":[3.949518999],"iteration":487,"passed_time":0.483981057,"remaining_time":0.507783404},
{"learn":[3.945431216],"iteration":488,"passed_time":0.4846597337,"remaining_time":0.5064644661},
{"learn":[3.943249086],"iteration":489,"passed_time":0.4853396021,"remaining_time":0.5051493818},
{"learn":[3.941981548],"iteration":490,"passed_time":0.4860307776,"remaining_time":0.5038486065},
{"learn":[3.936600517],"iteration":491,"passed_time":0.4866946721,"remaining_time":0.5025221411},
{"learn":[3.934476885],"iteration":492,"passed_time":0.4873817514,"remaining_time":0.5012222068},
{"learn":[3.93045798],"iteration":493,"passed_time":0.488079767,"remaining_time":0.4999359557},
{"learn":[3.925977375],"iteration":494,"passed_time":0.4887773521,"remaining_time":0.498651642},
{"learn":[3.92457993],"iteration":495,"passed_time":0.4895626835,"remaining_time":0.4974588558},
{"learn":[3.919849146],"iteration":496,"passed_time":0.4902694723,"remaining_time":0.4961882185},
{"learn":[3.919681964],"iteration":497,"passed_time":0.4909260359,"remaining_time":0.4948692169},
{"learn":[3.917633027],"iteration":498,"passed_time":0.4916024392,"remaining_time":0.4935727896},
{"learn":[3.916616419],"iteration":499,"passed_time":0.4922857428,"remaining_time":0.4922857428},
{"learn":[3.912896166],"iteration":500,"passed_time":0.4929664125,"remaining_time":0.4909984827},
{"learn":[3.912769674],"iteration":501,"passed_time":0.4936338523,"remaining_time":0.4897005149},
{"learn":[3.909373788],"iteration":502,"passed_time":0.4943299852,"remaining_time":0.4884334048},
{"learn":[3.906706036],"iteration":503,"passed_time":0.4950405396,"remaining_time":0.4871827533},
{"learn":[3.903895664],"iteration":504,"passed_time":0.4957431522,"remaining_time":0.4859264561},
{"learn":[3.902982967],"iteration":505,"passed_time":0.4964170517,"remaining_time":0.4846443153},
{"learn":[3.900905528],"iteration":506,"passed_time":0.4971173508,"remaining_time":0.4833902444},
{"learn":[3.897463465],"iteration":507,"passed_time":0.4977959173,"remaining_time":0.4821173057},
{"learn":[3.895918033],"iteration":508,"passed_time":0.4984558459,"remaining_time":0.4808287237},
{"learn":[3.893921936],"iteration":509,"passed_time":0.4991163954,"remaining_time":0.4795432035},
{"learn":[3.890237934],"iteration":510,"passed_time":0.4997960135,"remaining_time":0.478278377},
{"learn":[3.887311613],"iteration":511,"passed_time":0.5005228924,"remaining_time":0.4770608819},
{"learn":[3.884869735],"iteration":512,"passed_time":0.501272876,"remaining_time":0.4758672331},
{"learn":[3.882101231],"iteration":513,"passed_time":0.501957812,"remaining_time":0.4746138067},
{"learn":[3.88060368],"iteration":514,"passed_time":0.5026317716,"remaining_time":0.473352251},
{"learn":[3.877726076],"iteration":515,"passed_time":0.5033181198,"remaining_time":0.472104593},
{"learn":[3.874938145],"iteration":516,"passed_time":0.5041010126,"remaining_time":0.4709493019},
{"learn":[3.874340833],"iteration":517,"passed_time":0.5048958233,"remaining_time":0.4698065383},
{"learn":[3.873105224],"iteration":518,"passed_time":0.5055840643,"remaining_time":0.4685663486},
{"learn":[3.869800236],"iteration":519,"passed_time":0.5062768722,"remaining_time":0.4673324974},
{"learn":[3.867932518],"iteration":520,"passed_time":0.5069622189,"remaining_time":0.4660938634},
{"learn":[3.866666962],"iteration":521,"passed_time":0.5076362085,"remaining_time":0.4648469496},
{"learn":[3.865527652],"iteration":522,"passed_time":0.5083138136,"remaining_time":0.4636055241},
{"learn":[3.861900081],"iteration":523,"passed_time":0.5090303671,"remaining_time":0.4624016311},
{"learn":[3.858502887],"iteration":524,"passed_time":0.5097117778,"remaining_time":0.461167799},
{"learn":[3.858335097],"iteration":525,"passed_time":0.5103525477,"remaining_time":0.4598994442},
{"learn":[3.855719306],"iteration":526,"passed_time":0.5110488809,"remaining_time":0.4586833409},
{"learn":[3.855137428],"iteration":527,"passed_time":0.511696491,"remaining_time":0.4574256511},
{"learn":[3.851985706],"iteration":528,"passed_time":0.5123791337,"remaining_time":0.4562014593},
{"learn":[3.851051809],"iteration":529,"passed_time":0.5130420668,"remaining_time":0.4549618328},
{"learn":[3.850679146],"iteration":530,"passed_time":0.5136920004,"remaining_time":0.4537128968},
{"learn":[3.848179484],"iteration":531,"passed_time":0.5143745429,"remaining_time":0.4524948986},
{"learn":[3.844551071],"iteration":532,"passed_time":0.5151217673,"remaining_time":0.4513355822},
{"learn":[3.841604794],"iteration":533,"passed_time":0.5158125421,"remaining_time":0.450128548},
{"learn":[3.83969656],"iteration":534,"passed_time":0.5164701672,"remaining_time":0.4488946313},
{"learn":[3.836811463],"iteration":535,"passed_time":0.5171489441,"remaining_time":0.4476811755},
{"learn":[3.834182551],"iteration":536,"passed_time":0.517823795,"remaining_time":0.4464663261},
{"learn":[3.828012842],"iteration":537,"passed_time":0.5185402784,"remaining_time":0.4452892353},
{"learn":[3.826636176],"iteration":538,"passed_time":0.5192531613,"remaining_time":0.4441107743},
{"learn":[3.826189798],"iteration":539,"passed_time":0.5199077219,"remaining_time":0.4428843557},
{"learn":[3.824104738],"iteration":540,"passed_time":0.5205554922,"remaining_time":0.4416542901},
{"learn":[3.82300218],"iteration":541,"passed_time":0.5212085906,"remaining_time":0.4404308755},
{"learn":[3.817146402],"iteration":542,"passed_time":0.5219447033,"remaining_time":0.439279428},
{"learn":[3.814638044],"iteration":543,"passed_time":0.5226521932,"remaining_time":0.4381055149},
{"learn":[3.812979573],"iteration":544,"passed_time":0.523354295,"remaining_time":0.4369288151},
{"learn":[3.811938825],"iteration":545,"passed_time":0.5240042587,"remaining_time":0.4357105008},
{"learn":[3.811479418],"iteration":546,"passed_time":0.5246527802,"remaining_time":0.4344930702},
{"learn":[3.80742981],"iteration":547,"passed_time":0.5253552024,"remaining_time":0.4333221743},
{"learn":[3.805097043],"iteration":548,"passed_time":0.5260575145,"remaining_time":0.4321528945},
{"learn":[3.801577232],"iteration":549,"passed_time":0.52686552,"remaining_time":0.4310717891},
{"learn":[3.799762083],"iteration":550,"passed_time":0.5275835055,"remaining_time":0.4299183194},
{"learn":[3.796393455],"iteration":551,"passed_time":0.5282649263,"remaining_time":0.4287367518},
{"learn":[3.793486459],"iteration":552,"passed_time":0.5290621106,"remaining_time":0.4276505668},
{"learn":[3.792006091],"iteration":553,"passed_time":0.5298104666,"remaining_time":0.4265261157},
{"learn":[3.78932128],"iteration":554,"passed_time":0.530560991,"remaining_time":0.4254047585},
{"learn":[3.787581812],"iteration":555,"passed_time":0.5312455965,"remaining_time":0.4242320951},
{"learn":[3.785308865],"iteration":556,"passed_time":0.5319163814,"remaining_time":0.423050192},
{"learn":[3.78465475],"iteration":557,"passed_time":0.5326219784,"remaining_time":0.4218976962},
{"learn":[3.780498869],"iteration":558,"passed_time":0.5333248113,"remaining_time":0.4207446186},
{"learn":[3.778734909],"iteration":559,"passed_time":0.5340044494,"remaining_time":0.4195749246},
{"learn":[3.778652349],"iteration":560,"passed_time":0.5347095958,"remaining_time":0.4184269386},
{"learn":[3.777928006],"iteration":561,"passed_time":0.5353840662,"remaining_time":0.417256621},
{"learn":[3.776131406],"iteration":562,"passed_time":0.5360725475,"remaining_time":0.4160989401},
{"learn":[3.772925617],"iteration":563,"passed_time":0.5367535177,"remaining_time":0.4149371165},
{"learn":[3.7727745],"iteration":564,"passed_time":0.5374138268,"remaining_time":0.4137610879},
{"learn":[3.771763073],"iteration":565,"passed_time":0.5380757084,"remaining_time":0.4125880873},
{"learn":[3.768738162],"iteration":566,"passed_time":0.5388462633,"remaining_time":0.4114998801},
{"learn":[3.767220794],"iteration":567,"passed_time":0.5396093764,"remaining_time":0.4104071314},
{"learn":[3.766691102],"iteration":568,"passed_time":0.540283977,"remaining_time":0.4092484958},
{"learn":[3.766259335],"iteration":569,"passed_time":0.5409367048,"remaining_time":0.408075058},
{"learn":[3.76116362],"iteration":570,"passed_time":0.5416148407,"remaining_time":0.4069225336},
{"learn":[3.758633056],"iteration":571,"passed_time":0.5423074082,"remaining_time":0.4057824663},
{"learn":[3.754603809],"iteration":572,"passed_time":0.5430014479,"remaining_time":0.4046450581},
{"learn":[3.754070549],"iteration":573,"passed_time":0.5436225183,"remaining_time":0.4034550397},
{"learn":[3.750534319],"iteration":574,"passed_time":0.5443287863,"remaining_time":0.4023299725},
{"learn":[3.746491516],"iteration":575,"passed_time":0.5450290353,"remaining_time":0.4012019288},
{"learn":[3.744210544],"iteration":576,"passed_time":0.5457253384,"remaining_time":0.4000724752},
{"learn":[3.742929991],"iteration":577,"passed_time":0.5464261583,"remaining_time":0.398947818},
{"learn":[3.740402992],"iteration":578,"passed_time":0.5471141089,"remaining_time":0.3978152674},
{"learn":[3.739644243],"iteration":579,"passed_time":0.5478344074,"remaining_time":0.3967076743},
{"learn":[3.737529404],"iteration":580,"passed_time":0.5485281466,"remaining_time":0.3955822607},
{"learn":[3.737196923],"iteration":581,"passed_time":0.5492268539,"remaining_time":0.3944618985},
{"learn":[3.733954464],"iteration":582,"passed_time":0.5499166172,"remaining_time":0.3933365855},
{"learn":[3.731608623],"iteration":583,"passed_time":0.5505839268,"remaining_time":0.3921967698},
{"learn":[3.729843952],"iteration":584,"passed_time":0.5512644062,"remaining_time":0.3910679121},
{"learn":[3.727223798],"iteration":585,"passed_time":0.5519365932,"remaining_time":0.3899347263},
{"learn":[3.725351667],"iteration":586,"passed_time":0.5526077486,"remaining_time":0.3888023853},
{"learn":[3.725026912],"iteration":587,"passed_time":0.5532683583,"remaining_time":0.3876642238},
{"learn":[3.721974565],"iteration":588,"passed_time":0.553948387,"remaining_time":0.3865412344},
{"learn":[3.720269493],"iteration":589,"passed_time":0.5546272239,"remaining_time":0.3854189183},
{"learn":[3.718907466],"iteration":590,"passed_time":0.5553125305,"remaining_time":0.3843025803},
{"learn":[3.715602912],"iteration":591,"passed_time":0.5559911371,"remaining_time":0.383183081},
{"learn":[3.714463059],"iteration":592,"passed_time":0.5566724578,"remaining_time":0.3820669314},
{"learn":[3.710802077],"iteration":593,"passed_time":0.5574235329,"remaining_time":0.3809999232},
{"learn":[3.708032435],"iteration":594,"passed_time":0.5581784638,"remaining_time":0.3799366014},
{"learn":[3.703788939],"iteration":595,"passed_time":0.5588655431,"remaining_time":0.3788283212},
{"learn":[3.702500944],"iteration":596,"passed_time":0.5595401036,"remaining_time":0.3777130013},
{"learn":[3.698196925],"iteration":597,"passed_time":0.5602061414,"remaining_time":0.3765934261},
{"learn":[3.69658891],"iteration":598,"passed_time":0.5608662102,"remaining_time":0.3754713694},
{"learn":[3.696124066],"iteration":599,"passed_time":0.5615286626,"remaining_time":0.3743524417},
{"learn":[3.693537052],"iteration":600,"passed_time":0.5623114753,"remaining_time":0.3733149395},
{"learn":[3.691343275],"iteration":601,"passed_time":0.563089661,"remaining_time":0.3722752244},
{"learn":[3.690973831],"iteration":602,"passed_time":0.5637760893,"remaining_time":0.3711759659},
{"learn":[3.686151073],"iteration":603,"passed_time":0.5645187018,"remaining_time":0.3701149105},
{"learn":[3.683921982],"iteration":604,"passed_time":0.5652061316,"remaining_time":0.3690188793},
{"learn":[3.679975271],"iteration":605,"passed_time":0.5658962555,"remaining_time":0.3679259483},
{"learn":[3.674047638],"iteration":606,"passed_time":0.5666507457,"remaining_time":0.3668760182},
{"learn":[3.673151794],"iteration":607,"passed_time":0.5673221415,"remaining_time":0.365773486},
{"learn":[3.670953108],"iteration":608,"passed_time":0.5679856154,"remaining_time":0.3646672835},
{"learn":[3.6703947],"iteration":609,"passed_time":0.5686690192,"remaining_time":0.3635752746},
{"learn":[3.668433805],"iteration":610,"passed_time":0.5693246013,"remaining_time":0.3624668902},
{"learn":[3.668304956],"iteration":611,"passed_time":0.5699934132,"remaining_time":0.3613683731},
{"learn":[3.667880012],"iteration":612,"passed_time":0.5706785295,"remaining_time":0.3602815513},
{"learn":[3.667282264],"iteration":613,"passed_time":0.5714138806,"remaining_time":0.3592276187},
{"learn":[3.664611483],"iteration":614,"passed_time":0.5721440945,"remaining_time":0.3581715063},
{"learn":[3.662543394],"iteration":615,"passed_time":0.5728247742,"remaining_time":0.3570855735},
{"learn":[3.659041959],"iteration":616,"passed_time":0.5735251333,"remaining_time":0.3560131703},
{"learn":[3.656868545],"iteration":617,"passed_time":0.5742139152,"remaining_time":0.3549348149},
{"learn":[3.654785614],"iteration":618,"passed_time":0.5749070836,"remaining_time":0.3538604181},
{"learn":[3.654566096],"iteration":619,"passed_time":0.5755750041,"remaining_time":0.3527717767},
{"learn":[3.651007045],"iteration":620,"passed_time":0.5762730699,"remaining_time":0.351702888},
{"learn":[3.648921786],"iteration":621,"passed_time":0.5769771947,"remaining_time":0.3506388739},
{"learn":[3.647655706],"iteration":622,"passed_time":0.577660959,"remaining_time":0.3495636943},
{"learn":[3.647241144],"iteration":623,"passed_time":0.5783689095,"remaining_time":0.3485043429},
{"learn":[3.644195689],"iteration":624,"passed_time":0.5791426586,"remaining_time":0.3474855952},
{"learn":[3.642632246],"iteration":625,"passed_time":0.5798139443,"remaining_time":0.346406414},
{"learn":[3.642523322],"iteration":626,"passed_time":0.5804069532,"remaining_time":0.3452819674},
{"learn":[3.641494659],"iteration":627,"passed_time":0.5811062007,"remaining_time":0.3442221444},
{"learn":[3.63976496],"iteration":628,"passed_time":0.5817818929,"remaining_time":0.3431495744},
{"learn":[3.637945652],"iteration":629,"passed_time":0.5824793678,"remaining_time":0.3420910573},
{"learn":[3.636233667],"iteration":630,"passed_time":0.5831443239,"remaining_time":0.341014668},
{"learn":[3.635304404],"iteration":631,"passed_time":0.5837907623,"remaining_time":0.3399287983},
{"learn":[3.632234951],"iteration":632,"passed_time":0.5845005255,"remaining_time":0.3388810314},
{"learn":[3.631630987],"iteration":633,"passed_time":0.5851813655,"remaining_time":0.3378176337},
{"learn":[3.630301009],"iteration":634,"passed_time":0.5858876335,"remaining_time":0.3367700571},
{"learn":[3.629077964],"iteration":635,"passed_time":0.5865833958,"remaining_time":0.335717541},
{"learn":[3.628004522],"iteration":636,"passed_time":0.5872494636,"remaining_time":0.3346492234},
{"learn":[3.625062876],"iteration":637,"passed_time":0.5879226521,"remaining_time":0.333586207},
{"learn":[3.624917986],"iteration":638,"passed_time":0.5885655451,"remaining_time":0.3325072955},
{"learn":[3.622887087],"iteration":639,"passed_time":0.5892832102,"remaining_time":0.3314718058},
{"learn":[3.621220865],"iteration":640,"passed_time":0.5900578407,"remaining_time":0.3304692119},
{"learn":[3.621143844],"iteration":641,"passed_time":0.5906949751,"remaining_time":0.3293906559},
{"learn":[3.620822821],"iteration":642,"passed_time":0.5913830559,"remaining_time":0.3283417589},
{"learn":[3.619202826],"iteration":643,"passed_time":0.5920567551,"remaining_time":0.3272860323},
{"learn":[3.618204882],"iteration":644,"passed_time":0.5927349711,"remaining_time":0.3262339764},
{"learn":[3.614259666],"iteration":645,"passed_time":0.5934506633,"remaining_time":0.3252036142},
{"learn":[3.613415661],"iteration":646,"passed_time":0.594189109,"remaining_time":0.324186639},
{"learn":[3.611096773],"iteration":647,"passed_time":0.5948802443,"remaining_time":0.3231448241},
{"learn":[3.610820695],"iteration":648,"passed_time":0.5955220057,"remaining_time":0.3220773867},
{"learn":[3.609290065],"iteration":649,"passed_time":0.596240462,"remaining_time":0.3210525565},
{"learn":[3.60897947],"iteration":650,"passed_time":0.5969129194,"remaining_time":0.3200040075},
{"learn":[3.606570702],"iteration":651,"passed_time":0.5976114558,"remaining_time":0.3189705316},
{"learn":[3.606292637],"iteration":652,"passed_time":0.5983176237,"remaining_time":0.3179421369},
{"learn":[3.602753838],"iteration":653,"passed_time":0.5990622992,"remaining_time":0.3169351002},
{"learn":[3.599755869],"iteration":654,"passed_time":0.5997674456,"remaining_time":0.3159080439},
{"learn":[3.599509575],"iteration":655,"passed_time":0.6004344748,"remaining_time":0.3148619807},
{"learn":[3.595337722],"iteration":656,"passed_time":0.6011438475,"remaining_time":0.3138391776},
{"learn":[3.595168561],"iteration":657,"passed_time":0.6018011822,"remaining_time":0.3127902801},
{"learn":[3.59290559],"iteration":658,"passed_time":0.6024936796,"remaining_time":0.3117607659},
{"learn":[3.592015928],"iteration":659,"passed_time":0.6031720058,"remaining_time":0.3107249727},
{"learn":[3.590680403],"iteration":660,"passed_time":0.6038560104,"remaining_time":0.3096931733},
{"learn":[3.590361532],"iteration":661,"passed_time":0.6044831599,"remaining_time":0.3086333959},
{"learn":[3.589069739],"iteration":662,"passed_time":0.6051354872,"remaining_time":0.3075877212},
{"learn":[3.585010186],"iteration":663,"passed_time":0.6058973084,"remaining_time":0.306598638},
{"learn":[3.582997552],"iteration":664,"passed_time":0.6066034162,"remaining_time":0.3055821721},
{"learn":[3.582119256],"iteration":665,"passed_time":0.6073119075,"remaining_time":0.3045678335},
{"learn":[3.579019356],"iteration":666,"passed_time":0.607997124,"remaining_time":0.3035427921},
{"learn":[3.57719559],"iteration":667,"passed_time":0.6086811688,"remaining_time":0.3025181857},
{"learn":[3.574050046],"iteration":668,"passed_time":0.6094727451,"remaining_time":0.3015478007},
{"learn":[3.572204518],"iteration":669,"passed_time":0.610165533,"remaining_time":0.3005292924},
{"learn":[3.569508025],"iteration":670,"passed_time":0.6108603639,"remaining_time":0.2995127566},
{"learn":[3.566268704],"iteration":671,"passed_time":0.6115765668,"remaining_time":0.29850761},
{"learn":[3.562564052],"iteration":672,"passed_time":0.612272269,"remaining_time":0.297493361},
{"learn":[3.561173586],"iteration":673,"passed_time":0.6129737498,"remaining_time":0.2964828523},
{"learn":[3.559551904],"iteration":674,"passed_time":0.6136996573,"remaining_time":0.2954850202},
{"learn":[3.558593054],"iteration":675,"passed_time":0.6143946183,"remaining_time":0.2944731603},
{"learn":[3.555647008],"iteration":676,"passed_time":0.6150889284,"remaining_time":0.293461926},
{"learn":[3.553100059],"iteration":677,"passed_time":0.6157830282,"remaining_time":0.2924515267},
{"learn":[3.55085578],"iteration":678,"passed_time":0.6164954054,"remaining_time":0.2914506998},
{"learn":[3.550737965],"iteration":679,"passed_time":0.617141974,"remaining_time":0.2904197525},
{"learn":[3.549408772],"iteration":680,"passed_time":0.6178357633,"remaining_time":0.2894120536},
{"learn":[3.547390589],"iteration":681,"passed_time":0.6185125171,"remaining_time":0.288397332},
{"learn":[3.54723575],"iteration":682,"passed_time":0.619178625,"remaining_time":0.287378659},
{"learn":[3.543988891],"iteration":683,"passed_time":0.6198729051,"remaining_time":0.2863740322},
{"learn":[3.543868508],"iteration":684,"passed_time":0.6205481767,"remaining_time":0.2853615703},
{"learn":[3.542752124],"iteration":685,"passed_time":0.6213049008,"remaining_time":0.2843873744},
{"learn":[3.541334315],"iteration":686,"passed_time":0.622020633,"remaining_time":0.2833951356},
{"learn":[3.540208266],"iteration":687,"passed_time":0.6227398811,"remaining_time":0.2824052949},
{"learn":[3.537730983],"iteration":688,"passed_time":0.6235564187,"remaining_time":0.2814601542},
{"learn":[3.53419867],"iteration":689,"passed_time":0.6244200875,"remaining_time":0.2805365611},
{"learn":[3.532628335],"iteration":690,"passed_time":0.6251405468,"remaining_time":0.2795491013},
{"learn":[3.532204987],"iteration":691,"passed_time":0.625889659,"remaining_time":0.2785751662},
{"learn":[3.530618147],"iteration":692,"passed_time":0.6265627774,"remaining_time":0.2775682145},
{"learn":[3.528909306],"iteration":693,"passed_time":0.627310433,"remaining_time":0.27659509},
{"learn":[3.526700678],"iteration":694,"passed_time":0.6281248274,"remaining_time":0.2756519027},
{"learn":[3.526439574],"iteration":695,"passed_time":0.628781431,"remaining_time":0.2746401653},
{"learn":[3.525784216],"iteration":696,"passed_time":0.6294390161,"remaining_time":0.2736298736},
{"learn":[3.524112693],"iteration":697,"passed_time":0.6301800863,"remaining_time":0.2726567136},
{"learn":[3.522813541],"iteration":698,"passed_time":0.6309489581,"remaining_time":0.2716961894},
{"learn":[3.519148203],"iteration":699,"passed_time":0.6318010101,"remaining_time":0.2707718615},
{"learn":[3.517236747],"iteration":700,"passed_time":0.6325431062,"remaining_time":0.2698008399},
{"learn":[3.515603888],"iteration":701,"passed_time":0.6332716776,"remaining_time":0.2688247293},
{"learn":[3.51263524],"iteration":702,"passed_time":0.6339869391,"remaining_time":0.2678436997},
{"learn":[3.51123442],"iteration":703,"passed_time":0.6346457961,"remaining_time":0.2668397097},
{"learn":[3.50828027],"iteration":704,"passed_time":0.6353244929,"remaining_time":0.2658450006},
{"learn":[3.508265537],"iteration":705,"passed_time":0.63579651,"remaining_time":0.2647651189},
{"learn":[3.506774876],"iteration":706,"passed_time":0.6365061631,"remaining_time":0.2637854396},
{"learn":[3.50552068],"iteration":707,"passed_time":0.6371734627,"remaining_time":0.2627890552},
{"learn":[3.501973993],"iteration":708,"passed_time":0.637834523,"remaining_time":0.2617910384},
{"learn":[3.498880354],"iteration":709,"passed_time":0.6385048472,"remaining_time":0.2607977545},
{"learn":[3.497370959],"iteration":710,"passed_time":0.6392582453,"remaining_time":0.2598391461},
{"learn":[3.496050455],"iteration":711,"passed_time":0.639934979,"remaining_time":0.2588501039},
{"learn":[3.495630067],"iteration":712,"passed_time":0.6406070658,"remaining_time":0.2578600672},
{"learn":[3.49550669],"iteration":713,"passed_time":0.6412901592,"remaining_time":0.2568753299},
{"learn":[3.493652375],"iteration":714,"passed_time":0.6419663421,"remaining_time":0.2558886818},
{"learn":[3.491915684],"iteration":715,"passed_time":0.6426547233,"remaining_time":0.2549077394},
{"learn":[3.490303956],"iteration":716,"passed_time":0.6433288432,"remaining_time":0.2539219841},
{"learn":[3.488363853],"iteration":717,"passed_time":0.6440098834,"remaining_time":0.2529398149},
{"learn":[3.485483936],"iteration":718,"passed_time":0.6447230919,"remaining_time":0.2519710554},
{"learn":[3.483763466],"iteration":719,"passed_time":0.6454212077,"remaining_time":0.2509971363},
{"learn":[3.481642352],"iteration":720,"passed_time":0.6460755779,"remaining_time":0.2500070544},
{"learn":[3.479826119],"iteration":721,"passed_time":0.6467631279,"remaining_time":0.2490306781},
{"learn":[3.478588728],"iteration":722,"passed_time":0.6474601621,"remaining_time":0.2480587343},
{"learn":[3.475390887],"iteration":723,"passed_time":0.6481483931,"remaining_time":0.2470841941},
{"learn":[3.472636852],"iteration":724,"passed_time":0.6488268295,"remaining_time":0.2461067284},
{"learn":[3.47061883],"iteration":725,"passed_time":0.6495907839,"remaining_time":0.245162362},
{"learn":[3.46953149],"iteration":726,"passed_time":0.6502917039,"remaining_time":0.2441948214},
{"learn":[3.467217162],"iteration":727,"passed_time":0.6509872459,"remaining_time":0.2432260039},
{"learn":[3.465686216],"iteration":728,"passed_time":0.6516873146,"remaining_time":0.242259619},
{"learn":[3.462631216],"iteration":729,"passed_time":0.6523711891,"remaining_time":0.241287974},
{"learn":[3.461451053],"iteration":730,"passed_time":0.6530915382,"remaining_time":0.2403305387},
{"learn":[3.458950469],"iteration":731,"passed_time":0.6538432348,"remaining_time":0.2393852281},
{"learn":[3.458072145],"iteration":732,"passed_time":0.6544832536,"remaining_time":0.2383997663},
{"learn":[3.454364268],"iteration":733,"passed_time":0.6551701025,"remaining_time":0.237432217},
{"learn":[3.453243406],"iteration":734,"passed_time":0.6558523546,"remaining_time":0.2364637741},
{"learn":[3.453017963],"iteration":735,"passed_time":0.6565289281,"remaining_time":0.235494072},
{"learn":[3.45201581],"iteration":736,"passed_time":0.6572311901,"remaining_time":0.2345343324},
{"learn":[3.449510107],"iteration":737,"passed_time":0.6579779232,"remaining_time":0.2335910784},
{"learn":[3.447189189],"iteration":738,"passed_time":0.6586692789,"remaining_time":0.2326287981},
{"learn":[3.446423605],"iteration":739,"passed_time":0.6593616161,"remaining_time":0.2316675948},
{"learn":[3.445531987],"iteration":740,"passed_time":0.6600573083,"remaining_time":0.2307082899},
{"learn":[3.445328199],"iteration":741,"passed_time":0.6607357246,"remaining_time":0.2297436886},
{"learn":[3.443327544],"iteration":742,"passed_time":0.6614115169,"remaining_time":0.22877895},
{"learn":[3.441475798],"iteration":743,"passed_time":0.6620971741,"remaining_time":0.2278183825},
{"learn":[3.439046501],"iteration":744,"passed_time":0.662749962,"remaining_time":0.2268473024},
{"learn":[3.435899469],"iteration":745,"passed_time":0.6634644523,"remaining_time":0.2258980843},
{"learn":[3.433988352],"iteration":746,"passed_time":0.6641539753,"remaining_time":0.2249410385},
{"learn":[3.433413263],"iteration":747,"passed_time":0.6648883153,"remaining_time":0.2239998068},
{"learn":[3.429944699],"iteration":748,"passed_time":0.665593031,"remaining_time":0.2230492},
{"learn":[3.429291634],"iteration":749,"passed_time":0.6663014523,"remaining_time":0.2221004841},
{"learn":[3.429175603],"iteration":750,"passed_time":0.6669478306,"remaining_time":0.2211318373},
{"learn":[3.428780323],"iteration":751,"passed_time":0.6675878393,"remaining_time":0.220161947},
{"learn":[3.423893341],"iteration":752,"passed_time":0.6682634915,"remaining_time":0.2192046247},
{"learn":[3.421024316],"iteration":753,"passed_time":0.66897008,"remaining_time":0.2182581428},
{"learn":[3.420969872],"iteration":754,"passed_time":0.669646974,"remaining_time":0.2173026604},
{"learn":[3.419544785],"iteration":755,"passed_time":0.6703163969,"remaining_time":0.2163455037},
{"learn":[3.417057977],"iteration":756,"passed_time":0.6709836564,"remaining_time":0.2153884128},
{"learn":[3.415160245],"iteration":757,"passed_time":0.671742353,"remaining_time":0.2144612789},
{"learn":[3.412854597],"iteration":758,"passed_time":0.672405216,"remaining_time":0.2135041595},
{"learn":[3.410926347],"iteration":759,"passed_time":0.673110763,"remaining_time":0.2125612936},
{"learn":[3.408963843],"iteration":760,"passed_time":0.6738388737,"remaining_time":0.2116261377},
{"learn":[3.407629634],"iteration":761,"passed_time":0.6746844304,"remaining_time":0.2107282079},
{"learn":[3.404384724],"iteration":762,"passed_time":0.6754830067,"remaining_time":0.2098158225},
{"learn":[3.403041656],"iteration":763,"passed_time":0.6762352736,"remaining_time":0.2088894301},
{"learn":[3.401101731],"iteration":764,"passed_time":0.676945117,"remaining_time":0.2079504608},
{"learn":[3.400890668],"iteration":765,"passed_time":0.6776172038,"remaining_time":0.2070005557},
{"learn":[3.399289941],"iteration":766,"passed_time":0.6783133867,"remaining_time":0.2060586951},
{"learn":[3.399202366],"iteration":767,"passed_time":0.6789576318,"remaining_time":0.2051017846},
{"learn":[3.397447845],"iteration":768,"passed_time":0.6796143557,"remaining_time":0.2041494358},
{"learn":[3.394655341],"iteration":769,"passed_time":0.6802959467,"remaining_time":0.2032052828},
{"learn":[3.393228229],"iteration":770,"passed_time":0.6809420847,"remaining_time":0.2022512807},
{"learn":[3.389691197],"iteration":771,"passed_time":0.6815960543,"remaining_time":0.2013003891},
{"learn":[3.389626772],"iteration":772,"passed_time":0.6823063489,"remaining_time":0.2003668062},
{"learn":[3.388480222],"iteration":773,"passed_time":0.6831143188,"remaining_time":0.1994623205},
{"learn":[3.388215066],"iteration":774,"passed_time":0.6839123242,"remaining_time":0.1985551909},
{"learn":[3.386324358],"iteration":775,"passed_time":0.6846354681,"remaining_time":0.1976267331},
{"learn":[3.383913061],"iteration":776,"passed_time":0.6853826168,"remaining_time":0.1967056931},
{"learn":[3.382839768],"iteration":777,"passed_time":0.6860934422,"remaining_time":0.1957747354},
{"learn":[3.381961844],"iteration":778,"passed_time":0.6867939816,"remaining_time":0.1948414248},
{"learn":[3.381521703],"iteration":779,"passed_time":0.6875605895,"remaining_time":0.1939273458},
{"learn":[3.380918963],"iteration":780,"passed_time":0.6884715642,"remaining_time":0.1930541262},
{"learn":[3.377139006],"iteration":781,"passed_time":0.6893863345,"remaining_time":0.1921818682},
{"learn":[3.376004372],"iteration":782,"passed_time":0.690207725,"remaining_time":0.1912836224},
{"learn":[3.373826468],"iteration":783,"passed_time":0.6909390606,"remaining_time":0.1903607616},
{"learn":[3.373546786],"iteration":784,"passed_time":0.6916359846,"remaining_time":0.1894289639},
{"learn":[3.372109181],"iteration":785,"passed_time":0.6923100444,"remaining_time":0.1884915388},
{"learn":[3.370764924],"iteration":786,"passed_time":0.6929935283,"remaining_time":0.1875573336},
{"learn":[3.367833107],"iteration":787,"passed_time":0.6936866266,"remaining_time":0.1866263513},
{"learn":[3.36450404],"iteration":788,"passed_time":0.6943972712,"remaining_time":0.1857006644},
{"learn":[3.361794558],"iteration":789,"passed_time":0.6950700691,"remaining_time":0.1847654614},
{"learn":[3.356880529],"iteration":790,"passed_time":0.6957935128,"remaining_time":0.1838443036},
{"learn":[3.353843509],"iteration":791,"passed_time":0.6965309976,"remaining_time":0.1829273327},
{"learn":[3.353640253],"iteration":792,"passed_time":0.6971906658,"remaining_time":0.1819905017},
{"learn":[3.353055088],"iteration":793,"passed_time":0.6978831031,"remaining_time":0.1810628706},
{"learn":[3.351415617],"iteration":794,"passed_time":0.6986095914,"remaining_time":0.1801446116},
{"learn":[3.349169061],"iteration":795,"passed_time":0.6993486085,"remaining_time":0.1792300454},
{"learn":[3.346211014],"iteration":796,"passed_time":0.7000260734,"remaining_time":0.178300242},
{"learn":[3.344560452],"iteration":797,"passed_time":0.7006892869,"remaining_time":0.1773674636},
{"learn":[3.344445461],"iteration":798,"passed_time":0.7013510683,"remaining_time":0.1764349997},
{"learn":[3.342608898],"iteration":799,"passed_time":0.7020783278,"remaining_time":0.1755195819},
{"learn":[3.339572899],"iteration":800,"passed_time":0.7028121571,"remaining_time":0.1746062662},
{"learn":[3.339309302],"iteration":801,"passed_time":0.7034921257,"remaining_time":0.1736801009},
{"learn":[3.33698088],"iteration":802,"passed_time":0.7041921944,"remaining_time":0.1727594798},
{"learn":[3.334746342],"iteration":803,"passed_time":0.7048568501,"remaining_time":0.1718307744},
{"learn":[3.332048511],"iteration":804,"passed_time":0.7055647712,"remaining_time":0.1709132054},
{"learn":[3.331932544],"iteration":805,"passed_time":0.7062151054,"remaining_time":0.1699822958},
{"learn":[3.330541133],"iteration":806,"passed_time":0.70689908,"remaining_time":0.1690601269},
{"learn":[3.329124989],"iteration":807,"passed_time":0.7075700251,"remaining_time":0.1681354515},
{"learn":[3.32583918],"iteration":808,"passed_time":0.708257475,"remaining_time":0.1672153},
{"learn":[3.325287299],"iteration":809,"passed_time":0.7089403079,"remaining_time":0.1662946401},
{"learn":[3.322745162],"iteration":810,"passed_time":0.7096298609,"remaining_time":0.1653761328},
{"learn":[3.319733662],"iteration":811,"passed_time":0.710314837,"remaining_time":0.1644571298},
{"learn":[3.318080007],"iteration":812,"passed_time":0.7109729329,"remaining_time":0.1635325196},
{"learn":[3.317179538],"iteration":813,"passed_time":0.7116481243,"remaining_time":0.1626124707},
{"learn":[3.315685949],"iteration":814,"passed_time":0.7123350734,"remaining_time":0.1616956915},
{"learn":[3.314944576],"iteration":815,"passed_time":0.7130133796,"remaining_time":0.1607775268},
{"learn":[3.312369052],"iteration":816,"passed_time":0.7138768826,"remaining_time":0.1599014315},
{"learn":[3.312321621],"iteration":817,"passed_time":0.7144059952,"remaining_time":0.1589509671},
{"learn":[3.309465776],"iteration":818,"passed_time":0.7150950274,"remaining_time":0.1580368742},
{"learn":[3.308307377],"iteration":819,"passed_time":0.715762988,"remaining_time":0.1571187047},
{"learn":[3.308076804],"iteration":820,"passed_time":0.71641179,"remaining_time":0.1561969676},
{"learn":[3.305643326],"iteration":821,"passed_time":0.7171111777,"remaining_time":0.1552868487},
{"learn":[3.304154814],"iteration":822,"passed_time":0.7177726586,"remaining_time":0.1543690894},
{"learn":[3.303076321],"iteration":823,"passed_time":0.7184534084,"remaining_time":0.1534560678},
{"learn":[3.301746372],"iteration":824,"passed_time":0.7191365418,"remaining_time":0.1525441149},
{"learn":[3.301345455],"iteration":825,"passed_time":0.7198232505,"remaining_time":0.1516334692},
{"learn":[3.299181039],"iteration":826,"passed_time":0.7204885772,"remaining_time":0.1507188922},
{"learn":[3.297989357],"iteration":827,"passed_time":0.7212050505,"remaining_time":0.1498155419},
{"learn":[3.294775182],"iteration":828,"passed_time":0.7218792305,"remaining_time":0.1489039185},
{"learn":[3.293840636],"iteration":829,"passed_time":0.7225406513,"remaining_time":0.1479902539},
{"learn":[3.289279397],"iteration":830,"passed_time":0.7232865993,"remaining_time":0.1470943866},
{"learn":[3.286204979],"iteration":831,"passed_time":0.7239825018,"remaining_time":0.1461887744},
{"learn":[3.284833593],"iteration":832,"passed_time":0.7246545386,"remaining_time":0.1452788811},
{"learn":[3.283519914],"iteration":833,"passed_time":0.7253242919,"remaining_time":0.1443691037},
{"learn":[3.282853026],"iteration":834,"passed_time":0.7260010056,"remaining_time":0.1434612766},
{"learn":[3.281944673],"iteration":835,"passed_time":0.7266844294,"remaining_time":0.1425553187},
{"learn":[3.279764865],"iteration":836,"passed_time":0.7273855998,"remaining_time":0.1416533486},
{"learn":[3.277468839],"iteration":837,"passed_time":0.7280702054,"remaining_time":0.1407486555},
{"learn":[3.277124974],"iteration":838,"passed_time":0.7288027322,"remaining_time":0.1398536828},
{"learn":[3.275636037],"iteration":839,"passed_time":0.7294971124,"remaining_time":0.1389518309},
{"learn":[3.274413635],"iteration":840,"passed_time":0.730163691,"remaining_time":0.1380452163},
{"learn":[3.272636087],"iteration":841,"passed_time":0.730861937,"remaining_time":0.1371451141},
{"learn":[3.269644466],"iteration":842,"passed_time":0.7315561269,"remaining_time":0.1362447354},
{"learn":[3.26852083],"iteration":843,"passed_time":0.7322347836,"remaining_time":0.1353419742},
{"learn":[3.267820927],"iteration":844,"passed_time":0.7329038258,"remaining_time":0.1344379799},
{"learn":[3.267331099],"iteration":845,"passed_time":0.7336015511,"remaining_time":0.1335397623},
{"learn":[3.267231014],"iteration":846,"passed_time":0.7342306535,"remaining_time":0.1326296222},
{"learn":[3.267158695],"iteration":847,"passed_time":0.7348578731,"remaining_time":0.1317198074},
{"learn":[3.264718705],"iteration":848,"passed_time":0.7356071355,"remaining_time":0.1308323645},
{"learn":[3.261678512],"iteration":849,"passed_time":0.7363148057,"remaining_time":0.1299379069},
{"learn":[3.261368381],"iteration":850,"passed_time":0.7369900773,"remaining_time":0.1290382156},
{"learn":[3.260128799],"iteration":851,"passed_time":0.7376733709,"remaining_time":0.1281404447},
{"learn":[3.258972952],"iteration":852,"passed_time":0.7383542008,"remaining_time":0.1272427521},
{"learn":[3.258724846],"iteration":853,"passed_time":0.7390105841,"remaining_time":0.1263413879},
{"learn":[3.25686724],"iteration":854,"passed_time":0.7397390253,"remaining_time":0.1254528172},
{"learn":[3.255750259],"iteration":855,"passed_time":0.7404013675,"remaining_time":0.1245535011},
{"learn":[3.254915866],"iteration":856,"passed_time":0.7410837398,"remaining_time":0.1236580803},
{"learn":[3.254348625],"iteration":857,"passed_time":0.7417403534,"remaining_time":0.122758893},
{"learn":[3.253408514],"iteration":858,"passed_time":0.7424030662,"remaining_time":0.1218612716},
{"learn":[3.253291714],"iteration":859,"passed_time":0.7430743618,"remaining_time":0.1209655938},
{"learn":[3.250186342],"iteration":860,"passed_time":0.7437683815,"remaining_time":0.1200741057},
{"learn":[3.249141318],"iteration":861,"passed_time":0.7444563821,"remaining_time":0.1191821122},
{"learn":[3.246300388],"iteration":862,"passed_time":0.7451421995,"remaining_time":0.1182902449},
{"learn":[3.245205135],"iteration":863,"passed_time":0.7458044316,"remaining_time":0.117395142},
{"learn":[3.244403535],"iteration":864,"passed_time":0.7464583512,"remaining_time":0.1164992802},
{"learn":[3.244211781],"iteration":865,"passed_time":0.7472494663,"remaining_time":0.1156252061},
{"learn":[3.242286347],"iteration":866,"passed_time":0.7479544224,"remaining_time":0.1147381063},
{"learn":[3.239606746],"iteration":867,"passed_time":0.7486506353,"remaining_time":0.1138500966},
{"learn":[3.236773361],"iteration":868,"passed_time":0.7493256065,"remaining_time":0.1129593262},
{"learn":[3.234552446],"iteration":869,"passed_time":0.7500431258,"remaining_time":0.1120754096},
{"learn":[3.233724647],"iteration":870,"passed_time":0.7507198996,"remaining_time":0.1111858405},
{"learn":[3.230851485],"iteration":871,"passed_time":0.7514411801,"remaining_time":0.1103032925},
{"learn":[3.227728941],"iteration":872,"passed_time":0.7521241833,"remaining_time":0.1094155456},
{"learn":[3.225787575],"iteration":873,"passed_time":0.7527833608,"remaining_time":0.1085248323},
{"learn":[3.222797487],"iteration":874,"passed_time":0.7535154175,"remaining_time":0.1076450596},
{"learn":[3.22137014],"iteration":875,"passed_time":0.7542060521,"remaining_time":0.1067597608},
{"learn":[3.219701963],"iteration":876,"passed_time":0.7548811634,"remaining_time":0.1058727287},
{"learn":[3.21783327],"iteration":877,"passed_time":0.7555652983,"remaining_time":0.1049874332},
{"learn":[3.217713355],"iteration":878,"passed_time":0.756221972,"remaining_time":0.1040988153},
{"learn":[3.217666091],"iteration":879,"passed_time":0.75684815,"remaining_time":0.1032065659},
{"learn":[3.214962005],"iteration":880,"passed_time":0.7575423901,"remaining_time":0.102324114},
{"learn":[3.214081828],"iteration":881,"passed_time":0.7582090888,"remaining_time":0.1014384042},
{"learn":[3.213358337],"iteration":882,"passed_time":0.7589565185,"remaining_time":0.1005638875},
{"learn":[3.210850401],"iteration":883,"passed_time":0.7596311892,"remaining_time":0.0996801108},
{"learn":[3.207810328],"iteration":884,"passed_time":0.7602997307,"remaining_time":0.0987960102},
{"learn":[3.204935073],"iteration":885,"passed_time":0.7609600999,"remaining_time":0.09791134469},
{"learn":[3.20280198],"iteration":886,"passed_time":0.7616248257,"remaining_time":0.09702773992},
{"learn":[3.200663495],"iteration":887,"passed_time":0.7623228214,"remaining_time":0.09614882432},
{"learn":[3.197301669],"iteration":888,"passed_time":0.7630244825,"remaining_time":0.0952707734},
{"learn":[3.195666943],"iteration":889,"passed_time":0.7637782361,"remaining_time":0.09439955727},
{"learn":[3.193886506],"iteration":890,"passed_time":0.7644426815,"remaining_time":0.09351767933},
{"learn":[3.190601248],"iteration":891,"passed_time":0.7651859349,"remaining_time":0.09264583068},
{"learn":[3.188983797],"iteration":892,"passed_time":0.7658771504,"remaining_time":0.09176803481},
{"learn":[3.187365749],"iteration":893,"passed_time":0.7665973292,"remaining_time":0.09089409049},
{"learn":[3.186160771],"iteration":894,"passed_time":0.767297398,"remaining_time":0.09001813049},
{"learn":[3.185358981],"iteration":895,"passed_time":0.7679587988,"remaining_time":0.08913807486},
{"learn":[3.183832164],"iteration":896,"passed_time":0.7686564539,"remaining_time":0.08826266973},
{"learn":[3.183106966],"iteration":897,"passed_time":0.7693461371,"remaining_time":0.08738675499},
{"learn":[3.182838152],"iteration":898,"passed_time":0.7700203371,"remaining_time":0.08650951506},
{"learn":[3.180835453],"iteration":899,"passed_time":0.770708508,"remaining_time":0.08563427866},
{"learn":[3.179957348],"iteration":900,"passed_time":0.7713755572,"remaining_time":0.0847571367},
{"learn":[3.179752966],"iteration":901,"passed_time":0.772070979,"remaining_time":0.08388354318},
{"learn":[3.178851983],"iteration":902,"passed_time":0.772756516,"remaining_time":0.08300928245},
{"learn":[3.176748586],"iteration":903,"passed_time":0.7735283422,"remaining_time":0.08214460271},
{"learn":[3.172960988],"iteration":904,"passed_time":0.7743843796,"remaining_time":0.08128896803},
{"learn":[3.172794225],"iteration":905,"passed_time":0.7750200018,"remaining_time":0.08041046376},
{"learn":[3.169996507],"iteration":906,"passed_time":0.7757269008,"remaining_time":0.0795398035},
{"learn":[3.16813015],"iteration":907,"passed_time":0.7763958228,"remaining_time":0.07866565606},
{"learn":[3.166920871],"iteration":908,"passed_time":0.7770767229,"remaining_time":0.07779315928},
{"learn":[3.16531606],"iteration":909,"passed_time":0.7777896509,"remaining_time":0.07692425118},
{"learn":[3.162035247],"iteration":910,"passed_time":0.7784957386,"remaining_time":0.07605501727},
{"learn":[3.16189467],"iteration":911,"passed_time":0.7791667038,"remaining_time":0.07518275212},
{"learn":[3.161008416],"iteration":912,"passed_time":0.7798453604,"remaining_time":0.07431166085},
{"learn":[3.160560787],"iteration":913,"passed_time":0.780504628,"remaining_time":0.07343916631},
{"learn":[3.160416261],"iteration":914,"passed_time":0.7811736603,"remaining_time":0.07256804494},
{"learn":[3.15844291],"iteration":915,"passed_time":0.7818372343,"remaining_time":0.07169686428},
{"learn":[3.155040501],"iteration":916,"passed_time":0.7825291609,"remaining_time":0.07082870268},
{"learn":[3.154937548],"iteration":917,"passed_time":0.7831723043,"remaining_time":0.06995656749},
{"learn":[3.153721161],"iteration":918,"passed_time":0.7838675959,"remaining_time":0.06908952695},
{"learn":[3.153170511],"iteration":919,"passed_time":0.784521846,"remaining_time":0.06821929096},
{"learn":[3.153113601],"iteration":920,"passed_time":0.7851923405,"remaining_time":0.06735091737},
{"learn":[3.150607379],"iteration":921,"passed_time":0.7858836861,"remaining_time":0.066484737},
{"learn":[3.148408359],"iteration":922,"passed_time":0.7865647764,"remaining_time":0.06561807994},
{"learn":[3.147495728],"iteration":923,"passed_time":0.7872867279,"remaining_time":0.06475518542},
{"learn":[3.146946235],"iteration":924,"passed_time":0.7879477181,"remaining_time":0.06388765282},
{"learn":[3.14472738],"iteration":925,"passed_time":0.7888713768,"remaining_time":0.06304155711},
{"learn":[3.144469477],"iteration":926,"passed_time":0.7895678201,"remaining_time":0.06217740115},
{"learn":[3.142975516],"iteration":927,"passed_time":0.7902623005,"remaining_time":0.06131345435},
{"learn":[3.14079113],"iteration":928,"passed_time":0.7909313227,"remaining_time":0.06044792671},
{"learn":[3.138173032],"iteration":929,"passed_time":0.7917416266,"remaining_time":0.05959345577},
{"learn":[3.136352813],"iteration":930,"passed_time":0.792422096,"remaining_time":0.05872945717},
{"learn":[3.133735004],"iteration":931,"passed_time":0.7930834768,"remaining_time":0.05786445968},
{"learn":[3.1319496],"iteration":932,"passed_time":0.7937567353,"remaining_time":0.05700075163},
{"learn":[3.129865343],"iteration":933,"passed_time":0.7944865386,"remaining_time":0.05614144705},
{"learn":[3.129830206],"iteration":934,"passed_time":0.7949899127,"remaining_time":0.05526667842},
{"learn":[3.126676562],"iteration":935,"passed_time":0.7956800165,"remaining_time":0.05440547121},
{"learn":[3.12645665],"iteration":936,"passed_time":0.7963474964,"remaining_time":0.05354310808},
{"learn":[3.126378007],"iteration":937,"passed_time":0.7970225677,"remaining_time":0.05268166226},
{"learn":[3.124621914],"iteration":938,"passed_time":0.7976928719,"remaining_time":0.05182030371},
{"learn":[3.123379018],"iteration":939,"passed_time":0.7983740423,"remaining_time":0.05096004525},
{"learn":[3.123332451],"iteration":940,"passed_time":0.7990248873,"remaining_time":0.05009826605},
{"learn":[3.122432444],"iteration":941,"passed_time":0.7997024523,"remaining_time":0.04923857987},
{"learn":[3.121889006],"iteration":942,"passed_time":0.8003846543,"remaining_time":0.04837956023},
{"learn":[3.121070914],"iteration":943,"passed_time":0.8010745177,"remaining_time":0.0475213697},
{"learn":[3.118444705],"iteration":944,"passed_time":0.8017451824,"remaining_time":0.04666241802},
{"learn":[3.116820458],"iteration":945,"passed_time":0.8024189618,"remaining_time":0.04580404221},
{"learn":[3.114971041],"iteration":946,"passed_time":0.8031357205,"remaining_time":0.04494846165},
{"learn":[3.114685138],"iteration":947,"passed_time":0.8038720241,"remaining_time":0.04409424605},
{"learn":[3.113399363],"iteration":948,"passed_time":0.8045646511,"remaining_time":0.04323793172},
{"learn":[3.110575399],"iteration":949,"passed_time":0.8053431701,"remaining_time":0.04238648264},
{"learn":[3.110466553],"iteration":950,"passed_time":0.8060247211,"remaining_time":0.04153019068},
{"learn":[3.108691641],"iteration":951,"passed_time":0.8067124214,"remaining_time":0.04067457587},
{"learn":[3.107898017],"iteration":952,"passed_time":0.8073875227,"remaining_time":0.03981869209},
{"learn":[3.105551729],"iteration":953,"passed_time":0.8080530296,"remaining_time":0.0389627247},
{"learn":[3.104824945],"iteration":954,"passed_time":0.80873417,"remaining_time":0.03810789283},
{"learn":[3.103186704],"iteration":955,"passed_time":0.8094279093,"remaining_time":0.03725400419},
{"learn":[3.102330655],"iteration":956,"passed_time":0.8101274873,"remaining_time":0.03640071259},
{"learn":[3.102291298],"iteration":957,"passed_time":0.8107331145,"remaining_time":0.03554362298},
{"learn":[3.100363529],"iteration":958,"passed_time":0.8114242599,"remaining_time":0.03469071393},
{"learn":[3.097871596],"iteration":959,"passed_time":0.8121023257,"remaining_time":0.0338375969},
{"learn":[3.097372213],"iteration":960,"passed_time":0.8127702363,"remaining_time":0.03298443206},
{"learn":[3.095981813],"iteration":961,"passed_time":0.8134553025,"remaining_time":0.03213233004},
{"learn":[3.095347452],"iteration":962,"passed_time":0.8141467884,"remaining_time":0.03128082157},
{"learn":[3.094728409],"iteration":963,"passed_time":0.814825385,"remaining_time":0.03042916375},
{"learn":[3.094118537],"iteration":964,"passed_time":0.8158164519,"remaining_time":0.02958919774},
{"learn":[3.093793695],"iteration":965,"passed_time":0.8164192148,"remaining_time":0.02873525187},
{"learn":[3.092581602],"iteration":966,"passed_time":0.8171384723,"remaining_time":0.02788580102},
{"learn":[3.091694202],"iteration":967,"passed_time":0.8177935236,"remaining_time":0.02703449665},
{"learn":[3.090298312],"iteration":968,"passed_time":0.8185257405,"remaining_time":0.026186066},
{"learn":[3.090020107],"iteration":969,"passed_time":0.8191785484,"remaining_time":0.02533541902},
{"learn":[3.088949869],"iteration":970,"passed_time":0.8198610909,"remaining_time":0.0244860676},
{"learn":[3.086700204],"iteration":971,"passed_time":0.820543343,"remaining_time":0.02363705103},
{"learn":[3.086584317],"iteration":972,"passed_time":0.821251634,"remaining_time":0.02278909981},
{"learn":[3.084850742],"iteration":973,"passed_time":0.8219094294,"remaining_time":0.02194008744},
{"learn":[3.084239948],"iteration":974,"passed_time":0.8225682664,"remaining_time":0.02109149401},
{"learn":[3.082561673],"iteration":975,"passed_time":0.8232346647,"remaining_time":0.02024347536},
{"learn":[3.07991814],"iteration":976,"passed_time":0.8239207725,"remaining_time":0.0193962925},
{"learn":[3.079350277],"iteration":977,"passed_time":0.8246232048,"remaining_time":0.01854980624},
{"learn":[3.077637462],"iteration":978,"passed_time":0.8253025224,"remaining_time":0.01770311846},
{"learn":[3.076733301],"iteration":979,"passed_time":0.8259843939,"remaining_time":0.01685682437},
{"learn":[3.07594065],"iteration":980,"passed_time":0.8266747781,"remaining_time":0.01601103036},
{"learn":[3.072594655],"iteration":981,"passed_time":0.8273892084,"remaining_time":0.01516599364},
{"learn":[3.071977674],"iteration":982,"passed_time":0.828065842,"remaining_time":0.01432056899},
{"learn":[3.069532634],"iteration":983,"passed_time":0.8287641682,"remaining_time":0.01347584013},
{"learn":[3.068870784],"iteration":984,"passed_time":0.8294146426,"remaining_time":0.01263067984},
{"learn":[3.068801463],"iteration":985,"passed_time":0.8300752823,"remaining_time":0.01178605877},
{"learn":[3.067433249],"iteration":986,"passed_time":0.8307997375,"remaining_time":0.01094265105},
{"learn":[3.065611456],"iteration":987,"passed_time":0.8314713136,"remaining_time":0.01009884187},
{"learn":[3.063039162],"iteration":988,"passed_time":0.8322099657,"remaining_time":0.00925612702},
{"learn":[3.06177873],"iteration":989,"passed_time":0.832882363,"remaining_time":0.008412953161},
{"learn":[3.061689148],"iteration":990,"passed_time":0.8335430828,"remaining_time":0.007570017906},
{"learn":[3.058984039],"iteration":991,"passed_time":0.8342391856,"remaining_time":0.006727735367},
{"learn":[3.057492984],"iteration":992,"passed_time":0.834921047,"remaining_time":0.005885646857},
{"learn":[3.057290731],"iteration":993,"passed_time":0.8355577208,"remaining_time":0.005043607973},
{"learn":[3.056068348],"iteration":994,"passed_time":0.8362312598,"remaining_time":0.004202167135},
{"learn":[3.054987307],"iteration":995,"passed_time":0.8369124803,"remaining_time":0.003361094298},
{"learn":[3.054200234],"iteration":996,"passed_time":0.8375822737,"remaining_time":0.002520307744},
{"learn":[3.052732869],"iteration":997,"passed_time":0.8382599388,"remaining_time":0.001679879637},
{"learn":[3.051787862],"iteration":998,"passed_time":0.8389240737,"remaining_time":0.0008397638376},
{"learn":[3.051366222],"iteration":999,"passed_time":0.8396032211,"remaining_time":0}
]}